{
"type": "FeatureCollection",
"crs": { "type": "name", "properties": { "name": "urn:ogc:def:crs:OGC:1.3:CRS84" } },
"features": [
{ "type": "Feature", "properties": { "id": 270754, "count_point_id": 930065, "year": 2009, "region_id": 6, "local_authority_id": 147, "road_name": "B455", "road_category": "MB", "road_type": "Minor", "start_junction_road_name": null, "end_junction_road_name": null, "easting": 516240, "northing": 182200, "link_length_km": null, "link_length_miles": null, "sequence": null, "ramp": null, "estimation_method": "Counted", "estimation_method_detailed": "Manual count", "direction_of_travel": "S", "pedal_cycles": 56, "two_wheeled_motor_vehicles": 142, "cars_and_taxis": 12365, "buses_and_coaches": 484, "lgvs": 1241, "hgvs_2_rigid_axle": 174, "hgvs_3_rigid_axle": 32, "hgvs_4_or_more_rigid_axle": 28, "hgvs_3_or_4_articulated_axle": 2, "hgvs_5_articulated_axle": 1, "hgvs_6_articulated_axle": 1, "all_hgvs": 238, "all_motor_vehicles": 14470 }, "geometry": { "type": "Point", "coordinates": [ -0.32578665, 51.52676005 ] } },
{ "type": "Feature", "properties": { "id": 270753, "count_point_id": 930065, "year": 2009, "region_id": 6, "local_authority_id": 147, "road_name": "B455", "road_category": "MB", "road_type": "Minor", "start_junction_road_name": null, "end_junction_road_name": null, "easting": 516240, "northing": 182200, "link_length_km": null, "link_length_miles": null, "sequence": null, "ramp": null, "estimation_method": "Counted", "estimation_method_detailed": "Manual count", "direction_of_travel": "N", "pedal_cycles": 47, "two_wheeled_motor_vehicles": 121, "cars_and_taxis": 10278, "buses_and_coaches": 446, "lgvs": 977, "hgvs_2_rigid_axle": 178, "hgvs_3_rigid_axle": 20, "hgvs_4_or_more_rigid_axle": 19, "hgvs_3_or_4_articulated_axle": 3, "hgvs_5_articulated_axle": 2, "hgvs_6_articulated_axle": 1, "all_hgvs": 223, "all_motor_vehicles": 12045 }, "geometry": { "type": "Point", "coordinates": [ -0.32578665, 51.52676005 ] } }
]
}
