{
"type": "FeatureCollection",
"crs": { "type": "name", "properties": { "name": "urn:ogc:def:crs:OGC:1.3:CRS84" } },
"features": [
{ "type": "Feature", "properties": { "id": 260492, "count_point_id": 931007, "year": 2008, "region_id": 11, "local_authority_id": 163, "road_name": "U", "road_category": "MCU", "road_type": "Minor", "start_junction_road_name": null, "end_junction_road_name": null, "easting": 441660, "northing": 518070, "link_length_km": null, "link_length_miles": null, "sequence": null, "ramp": null, "estimation_method": "Counted", "estimation_method_detailed": "Manual count", "direction_of_travel": "N", "pedal_cycles": 13, "two_wheeled_motor_vehicles": 12, "cars_and_taxis": 2322, "buses_and_coaches": 33, "lgvs": 200, "hgvs_2_rigid_axle": 13, "hgvs_3_rigid_axle": 3, "hgvs_4_or_more_rigid_axle": 0, "hgvs_3_or_4_articulated_axle": 1, "hgvs_5_articulated_axle": 0, "hgvs_6_articulated_axle": 0, "all_hgvs": 17, "all_motor_vehicles": 2584 }, "geometry": { "type": "Point", "coordinates": [ -1.35736142, 54.5561653 ] } },
{ "type": "Feature", "properties": { "id": 260493, "count_point_id": 931007, "year": 2008, "region_id": 11, "local_authority_id": 163, "road_name": "U", "road_category": "MCU", "road_type": "Minor", "start_junction_road_name": null, "end_junction_road_name": null, "easting": 441660, "northing": 518070, "link_length_km": null, "link_length_miles": null, "sequence": null, "ramp": null, "estimation_method": "Counted", "estimation_method_detailed": "Manual count", "direction_of_travel": "S", "pedal_cycles": 15, "two_wheeled_motor_vehicles": 9, "cars_and_taxis": 2172, "buses_and_coaches": 35, "lgvs": 186, "hgvs_2_rigid_axle": 13, "hgvs_3_rigid_axle": 2, "hgvs_4_or_more_rigid_axle": 0, "hgvs_3_or_4_articulated_axle": 1, "hgvs_5_articulated_axle": 0, "hgvs_6_articulated_axle": 0, "all_hgvs": 16, "all_motor_vehicles": 2418 }, "geometry": { "type": "Point", "coordinates": [ -1.35736142, 54.5561653 ] } }
]
}
