{
"type": "FeatureCollection",
"crs": { "type": "name", "properties": { "name": "urn:ogc:def:crs:OGC:1.3:CRS84" } },
"features": [
{ "type": "Feature", "properties": { "id": 215529, "count_point_id": 941702, "year": 2015, "region_id": 7, "local_authority_id": 120, "road_name": "U", "road_category": "MCU", "road_type": "Minor", "start_junction_road_name": null, "end_junction_road_name": null, "easting": 506337, "northing": 224853, "link_length_km": null, "link_length_miles": null, "sequence": null, "ramp": null, "estimation_method": "Counted", "estimation_method_detailed": "Manual count", "direction_of_travel": "W", "pedal_cycles": 0, "two_wheeled_motor_vehicles": 0, "cars_and_taxis": 126, "buses_and_coaches": 0, "lgvs": 25, "hgvs_2_rigid_axle": 0, "hgvs_3_rigid_axle": 0, "hgvs_4_or_more_rigid_axle": 0, "hgvs_3_or_4_articulated_axle": 0, "hgvs_5_articulated_axle": 0, "hgvs_6_articulated_axle": 0, "all_hgvs": 0, "all_motor_vehicles": 151 }, "geometry": { "type": "Point", "coordinates": [ -0.45547448, 51.91206981 ] } },
{ "type": "Feature", "properties": { "id": 170834, "count_point_id": 941702, "year": 2014, "region_id": 7, "local_authority_id": 120, "road_name": "U", "road_category": "MCU", "road_type": "Minor", "start_junction_road_name": null, "end_junction_road_name": null, "easting": 506337, "northing": 224853, "link_length_km": null, "link_length_miles": null, "sequence": null, "ramp": null, "estimation_method": "Counted", "estimation_method_detailed": "Manual count", "direction_of_travel": "W", "pedal_cycles": 0, "two_wheeled_motor_vehicles": 2, "cars_and_taxis": 124, "buses_and_coaches": 0, "lgvs": 7, "hgvs_2_rigid_axle": 1, "hgvs_3_rigid_axle": 0, "hgvs_4_or_more_rigid_axle": 0, "hgvs_3_or_4_articulated_axle": 0, "hgvs_5_articulated_axle": 0, "hgvs_6_articulated_axle": 0, "all_hgvs": 1, "all_motor_vehicles": 134 }, "geometry": { "type": "Point", "coordinates": [ -0.45547448, 51.91206981 ] } },
{ "type": "Feature", "properties": { "id": 215528, "count_point_id": 941702, "year": 2015, "region_id": 7, "local_authority_id": 120, "road_name": "U", "road_category": "MCU", "road_type": "Minor", "start_junction_road_name": null, "end_junction_road_name": null, "easting": 506337, "northing": 224853, "link_length_km": null, "link_length_miles": null, "sequence": null, "ramp": null, "estimation_method": "Counted", "estimation_method_detailed": "Manual count", "direction_of_travel": "E", "pedal_cycles": 2, "two_wheeled_motor_vehicles": 0, "cars_and_taxis": 128, "buses_and_coaches": 0, "lgvs": 19, "hgvs_2_rigid_axle": 0, "hgvs_3_rigid_axle": 0, "hgvs_4_or_more_rigid_axle": 0, "hgvs_3_or_4_articulated_axle": 0, "hgvs_5_articulated_axle": 0, "hgvs_6_articulated_axle": 0, "all_hgvs": 0, "all_motor_vehicles": 147 }, "geometry": { "type": "Point", "coordinates": [ -0.45547448, 51.91206981 ] } },
{ "type": "Feature", "properties": { "id": 170833, "count_point_id": 941702, "year": 2014, "region_id": 7, "local_authority_id": 120, "road_name": "U", "road_category": "MCU", "road_type": "Minor", "start_junction_road_name": null, "end_junction_road_name": null, "easting": 506337, "northing": 224853, "link_length_km": null, "link_length_miles": null, "sequence": null, "ramp": null, "estimation_method": "Counted", "estimation_method_detailed": "Manual count", "direction_of_travel": "E", "pedal_cycles": 0, "two_wheeled_motor_vehicles": 1, "cars_and_taxis": 146, "buses_and_coaches": 0, "lgvs": 9, "hgvs_2_rigid_axle": 1, "hgvs_3_rigid_axle": 0, "hgvs_4_or_more_rigid_axle": 0, "hgvs_3_or_4_articulated_axle": 0, "hgvs_5_articulated_axle": 0, "hgvs_6_articulated_axle": 0, "all_hgvs": 1, "all_motor_vehicles": 157 }, "geometry": { "type": "Point", "coordinates": [ -0.45547448, 51.91206981 ] } }
]
}
