{
"type": "FeatureCollection",
"crs": { "type": "name", "properties": { "name": "urn:ogc:def:crs:OGC:1.3:CRS84" } },
"features": [
{ "type": "Feature", "properties": { "id": 15570, "count_point_id": 910018, "year": 2000, "region_id": 5, "local_authority_id": 77, "road_name": "C", "road_category": "MCU", "road_type": "Minor", "start_junction_road_name": null, "end_junction_road_name": null, "easting": 360842, "northing": 524160, "link_length_km": null, "link_length_miles": null, "sequence": null, "ramp": null, "estimation_method": "Estimated", "estimation_method_detailed": "Estimated using previous year's AADF on this link", "direction_of_travel": "C", "pedal_cycles": 7, "two_wheeled_motor_vehicles": 7, "cars_and_taxis": 856, "buses_and_coaches": 8, "lgvs": 147, "hgvs_2_rigid_axle": 32, "hgvs_3_rigid_axle": 7, "hgvs_4_or_more_rigid_axle": 2, "hgvs_3_or_4_articulated_axle": 1, "hgvs_5_articulated_axle": 11, "hgvs_6_articulated_axle": 4, "all_hgvs": 57, "all_motor_vehicles": 1075 }, "geometry": { "type": "Point", "coordinates": [ -2.60779581, 54.6110731 ] } },
{ "type": "Feature", "properties": { "id": 265986, "count_point_id": 910018, "year": 2009, "region_id": 5, "local_authority_id": 77, "road_name": "C", "road_category": "MCU", "road_type": "Minor", "start_junction_road_name": null, "end_junction_road_name": null, "easting": 360842, "northing": 524160, "link_length_km": null, "link_length_miles": null, "sequence": null, "ramp": null, "estimation_method": "Counted", "estimation_method_detailed": "Manual count", "direction_of_travel": "W", "pedal_cycles": 5, "two_wheeled_motor_vehicles": 2, "cars_and_taxis": 356, "buses_and_coaches": 1, "lgvs": 71, "hgvs_2_rigid_axle": 9, "hgvs_3_rigid_axle": 6, "hgvs_4_or_more_rigid_axle": 1, "hgvs_3_or_4_articulated_axle": 1, "hgvs_5_articulated_axle": 0, "hgvs_6_articulated_axle": 2, "all_hgvs": 19, "all_motor_vehicles": 449 }, "geometry": { "type": "Point", "coordinates": [ -2.60779581, 54.6110731 ] } },
{ "type": "Feature", "properties": { "id": 20833, "count_point_id": 910018, "year": 2002, "region_id": 5, "local_authority_id": 77, "road_name": "C", "road_category": "MCU", "road_type": "Minor", "start_junction_road_name": null, "end_junction_road_name": null, "easting": 360842, "northing": 524160, "link_length_km": null, "link_length_miles": null, "sequence": null, "ramp": null, "estimation_method": "Counted", "estimation_method_detailed": "Manual count", "direction_of_travel": "S", "pedal_cycles": 2, "two_wheeled_motor_vehicles": 4, "cars_and_taxis": 666, "buses_and_coaches": 8, "lgvs": 79, "hgvs_2_rigid_axle": 47, "hgvs_3_rigid_axle": 8, "hgvs_4_or_more_rigid_axle": 0, "hgvs_3_or_4_articulated_axle": 1, "hgvs_5_articulated_axle": 1, "hgvs_6_articulated_axle": 0, "all_hgvs": 57, "all_motor_vehicles": 814 }, "geometry": { "type": "Point", "coordinates": [ -2.60779581, 54.6110731 ] } },
{ "type": "Feature", "properties": { "id": 265985, "count_point_id": 910018, "year": 2009, "region_id": 5, "local_authority_id": 77, "road_name": "C", "road_category": "MCU", "road_type": "Minor", "start_junction_road_name": null, "end_junction_road_name": null, "easting": 360842, "northing": 524160, "link_length_km": null, "link_length_miles": null, "sequence": null, "ramp": null, "estimation_method": "Counted", "estimation_method_detailed": "Manual count", "direction_of_travel": "E", "pedal_cycles": 3, "two_wheeled_motor_vehicles": 2, "cars_and_taxis": 313, "buses_and_coaches": 3, "lgvs": 56, "hgvs_2_rigid_axle": 11, "hgvs_3_rigid_axle": 5, "hgvs_4_or_more_rigid_axle": 1, "hgvs_3_or_4_articulated_axle": 3, "hgvs_5_articulated_axle": 1, "hgvs_6_articulated_axle": 1, "all_hgvs": 22, "all_motor_vehicles": 396 }, "geometry": { "type": "Point", "coordinates": [ -2.60779581, 54.6110731 ] } },
{ "type": "Feature", "properties": { "id": 20832, "count_point_id": 910018, "year": 2002, "region_id": 5, "local_authority_id": 77, "road_name": "C", "road_category": "MCU", "road_type": "Minor", "start_junction_road_name": null, "end_junction_road_name": null, "easting": 360842, "northing": 524160, "link_length_km": null, "link_length_miles": null, "sequence": null, "ramp": null, "estimation_method": "Counted", "estimation_method_detailed": "Manual count", "direction_of_travel": "N", "pedal_cycles": 8, "two_wheeled_motor_vehicles": 10, "cars_and_taxis": 497, "buses_and_coaches": 5, "lgvs": 66, "hgvs_2_rigid_axle": 44, "hgvs_3_rigid_axle": 5, "hgvs_4_or_more_rigid_axle": 0, "hgvs_3_or_4_articulated_axle": 1, "hgvs_5_articulated_axle": 1, "hgvs_6_articulated_axle": 0, "all_hgvs": 51, "all_motor_vehicles": 629 }, "geometry": { "type": "Point", "coordinates": [ -2.60779581, 54.6110731 ] } }
]
}
