{
"type": "FeatureCollection",
"crs": { "type": "name", "properties": { "name": "urn:ogc:def:crs:OGC:1.3:CRS84" } },
"features": [
{ "type": "Feature", "properties": { "id": 261269, "count_point_id": 941601, "year": 2009, "region_id": 7, "local_authority_id": 78, "road_name": "U", "road_category": "MCU", "road_type": "Minor", "start_junction_road_name": null, "end_junction_road_name": null, "easting": 517160, "northing": 209640, "link_length_km": null, "link_length_miles": null, "sequence": null, "ramp": null, "estimation_method": "Counted", "estimation_method_detailed": "Manual count", "direction_of_travel": "C", "pedal_cycles": 91, "two_wheeled_motor_vehicles": 15, "cars_and_taxis": 4834, "buses_and_coaches": 74, "lgvs": 381, "hgvs_2_rigid_axle": 34, "hgvs_3_rigid_axle": 7, "hgvs_4_or_more_rigid_axle": 1, "hgvs_3_or_4_articulated_axle": 1, "hgvs_5_articulated_axle": 0, "hgvs_6_articulated_axle": 0, "all_hgvs": 43, "all_motor_vehicles": 5347 }, "geometry": { "type": "Point", "coordinates": [ -0.30334836, 51.77318188 ] } },
{ "type": "Feature", "properties": { "id": 211995, "count_point_id": 941601, "year": 2015, "region_id": 7, "local_authority_id": 78, "road_name": "U", "road_category": "MCU", "road_type": "Minor", "start_junction_road_name": null, "end_junction_road_name": null, "easting": 517160, "northing": 209640, "link_length_km": null, "link_length_miles": null, "sequence": null, "ramp": null, "estimation_method": "Counted", "estimation_method_detailed": "Manual count", "direction_of_travel": "W", "pedal_cycles": 12, "two_wheeled_motor_vehicles": 7, "cars_and_taxis": 2239, "buses_and_coaches": 41, "lgvs": 265, "hgvs_2_rigid_axle": 7, "hgvs_3_rigid_axle": 1, "hgvs_4_or_more_rigid_axle": 0, "hgvs_3_or_4_articulated_axle": 0, "hgvs_5_articulated_axle": 0, "hgvs_6_articulated_axle": 0, "all_hgvs": 7, "all_motor_vehicles": 2560 }, "geometry": { "type": "Point", "coordinates": [ -0.30334836, 51.77318188 ] } },
{ "type": "Feature", "properties": { "id": 171891, "count_point_id": 941601, "year": 2014, "region_id": 7, "local_authority_id": 78, "road_name": "U", "road_category": "MCU", "road_type": "Minor", "start_junction_road_name": null, "end_junction_road_name": null, "easting": 517160, "northing": 209640, "link_length_km": null, "link_length_miles": null, "sequence": null, "ramp": null, "estimation_method": "Counted", "estimation_method_detailed": "Manual count", "direction_of_travel": "W", "pedal_cycles": 20, "two_wheeled_motor_vehicles": 15, "cars_and_taxis": 2086, "buses_and_coaches": 30, "lgvs": 188, "hgvs_2_rigid_axle": 14, "hgvs_3_rigid_axle": 0, "hgvs_4_or_more_rigid_axle": 4, "hgvs_3_or_4_articulated_axle": 0, "hgvs_5_articulated_axle": 0, "hgvs_6_articulated_axle": 0, "all_hgvs": 18, "all_motor_vehicles": 2336 }, "geometry": { "type": "Point", "coordinates": [ -0.30334836, 51.77318188 ] } },
{ "type": "Feature", "properties": { "id": 171890, "count_point_id": 941601, "year": 2014, "region_id": 7, "local_authority_id": 78, "road_name": "U", "road_category": "MCU", "road_type": "Minor", "start_junction_road_name": null, "end_junction_road_name": null, "easting": 517160, "northing": 209640, "link_length_km": null, "link_length_miles": null, "sequence": null, "ramp": null, "estimation_method": "Counted", "estimation_method_detailed": "Manual count", "direction_of_travel": "E", "pedal_cycles": 31, "two_wheeled_motor_vehicles": 11, "cars_and_taxis": 2210, "buses_and_coaches": 26, "lgvs": 199, "hgvs_2_rigid_axle": 15, "hgvs_3_rigid_axle": 1, "hgvs_4_or_more_rigid_axle": 3, "hgvs_3_or_4_articulated_axle": 0, "hgvs_5_articulated_axle": 0, "hgvs_6_articulated_axle": 0, "all_hgvs": 19, "all_motor_vehicles": 2465 }, "geometry": { "type": "Point", "coordinates": [ -0.30334836, 51.77318188 ] } },
{ "type": "Feature", "properties": { "id": 211994, "count_point_id": 941601, "year": 2015, "region_id": 7, "local_authority_id": 78, "road_name": "U", "road_category": "MCU", "road_type": "Minor", "start_junction_road_name": null, "end_junction_road_name": null, "easting": 517160, "northing": 209640, "link_length_km": null, "link_length_miles": null, "sequence": null, "ramp": null, "estimation_method": "Counted", "estimation_method_detailed": "Manual count", "direction_of_travel": "E", "pedal_cycles": 12, "two_wheeled_motor_vehicles": 10, "cars_and_taxis": 2053, "buses_and_coaches": 38, "lgvs": 234, "hgvs_2_rigid_axle": 10, "hgvs_3_rigid_axle": 2, "hgvs_4_or_more_rigid_axle": 0, "hgvs_3_or_4_articulated_axle": 0, "hgvs_5_articulated_axle": 0, "hgvs_6_articulated_axle": 0, "all_hgvs": 12, "all_motor_vehicles": 2346 }, "geometry": { "type": "Point", "coordinates": [ -0.30334836, 51.77318188 ] } }
]
}
