{
"type": "FeatureCollection",
"crs": { "type": "name", "properties": { "name": "urn:ogc:def:crs:OGC:1.3:CRS84" } },
"features": [
{ "type": "Feature", "properties": { "id": 255205, "count_point_id": 930805, "year": 2009, "region_id": 9, "local_authority_id": 80, "road_name": "U", "road_category": "MCU", "road_type": "Minor", "start_junction_road_name": null, "end_junction_road_name": null, "easting": 550570, "northing": 169490, "link_length_km": null, "link_length_miles": null, "sequence": null, "ramp": null, "estimation_method": "Counted", "estimation_method_detailed": "Manual count", "direction_of_travel": "N", "pedal_cycles": 7, "two_wheeled_motor_vehicles": 14, "cars_and_taxis": 850, "buses_and_coaches": 10, "lgvs": 108, "hgvs_2_rigid_axle": 3, "hgvs_3_rigid_axle": 0, "hgvs_4_or_more_rigid_axle": 1, "hgvs_3_or_4_articulated_axle": 0, "hgvs_5_articulated_axle": 2, "hgvs_6_articulated_axle": 0, "all_hgvs": 6, "all_motor_vehicles": 988 }, "geometry": { "type": "Point", "coordinates": [ 0.16333661, 51.40445821 ] } },
{ "type": "Feature", "properties": { "id": 255206, "count_point_id": 930805, "year": 2009, "region_id": 9, "local_authority_id": 80, "road_name": "U", "road_category": "MCU", "road_type": "Minor", "start_junction_road_name": null, "end_junction_road_name": null, "easting": 550570, "northing": 169490, "link_length_km": null, "link_length_miles": null, "sequence": null, "ramp": null, "estimation_method": "Counted", "estimation_method_detailed": "Manual count", "direction_of_travel": "S", "pedal_cycles": 8, "two_wheeled_motor_vehicles": 33, "cars_and_taxis": 1860, "buses_and_coaches": 15, "lgvs": 197, "hgvs_2_rigid_axle": 13, "hgvs_3_rigid_axle": 1, "hgvs_4_or_more_rigid_axle": 0, "hgvs_3_or_4_articulated_axle": 0, "hgvs_5_articulated_axle": 2, "hgvs_6_articulated_axle": 0, "all_hgvs": 16, "all_motor_vehicles": 2121 }, "geometry": { "type": "Point", "coordinates": [ 0.16333661, 51.40445821 ] } }
]
}
