{
"type": "FeatureCollection",
"crs": { "type": "name", "properties": { "name": "urn:ogc:def:crs:OGC:1.3:CRS84" } },
"features": [
{ "type": "Feature", "properties": { "id": 259932, "count_point_id": 931325, "year": 2008, "region_id": 9, "local_authority_id": 142, "road_name": "C", "road_category": "MCU", "road_type": "Minor", "start_junction_road_name": null, "end_junction_road_name": null, "easting": 427620, "northing": 206520, "link_length_km": null, "link_length_miles": null, "sequence": null, "ramp": null, "estimation_method": "Counted", "estimation_method_detailed": "Manual count", "direction_of_travel": "E", "pedal_cycles": 38, "two_wheeled_motor_vehicles": 19, "cars_and_taxis": 2174, "buses_and_coaches": 35, "lgvs": 298, "hgvs_2_rigid_axle": 22, "hgvs_3_rigid_axle": 2, "hgvs_4_or_more_rigid_axle": 2, "hgvs_3_or_4_articulated_axle": 3, "hgvs_5_articulated_axle": 1, "hgvs_6_articulated_axle": 3, "all_hgvs": 33, "all_motor_vehicles": 2559 }, "geometry": { "type": "Point", "coordinates": [ -1.60125076, 51.75669412 ] } },
{ "type": "Feature", "properties": { "id": 259933, "count_point_id": 931325, "year": 2008, "region_id": 9, "local_authority_id": 142, "road_name": "C", "road_category": "MCU", "road_type": "Minor", "start_junction_road_name": null, "end_junction_road_name": null, "easting": 427620, "northing": 206520, "link_length_km": null, "link_length_miles": null, "sequence": null, "ramp": null, "estimation_method": "Counted", "estimation_method_detailed": "Manual count", "direction_of_travel": "W", "pedal_cycles": 45, "two_wheeled_motor_vehicles": 23, "cars_and_taxis": 2248, "buses_and_coaches": 12, "lgvs": 272, "hgvs_2_rigid_axle": 17, "hgvs_3_rigid_axle": 5, "hgvs_4_or_more_rigid_axle": 2, "hgvs_3_or_4_articulated_axle": 0, "hgvs_5_articulated_axle": 1, "hgvs_6_articulated_axle": 0, "all_hgvs": 25, "all_motor_vehicles": 2580 }, "geometry": { "type": "Point", "coordinates": [ -1.60125076, 51.75669412 ] } }
]
}
