{
"type": "FeatureCollection",
"crs": { "type": "name", "properties": { "name": "urn:ogc:def:crs:OGC:1.3:CRS84" } },
"features": [
{ "type": "Feature", "properties": { "id": 259930, "count_point_id": 931326, "year": 2008, "region_id": 9, "local_authority_id": 142, "road_name": "C", "road_category": "MCU", "road_type": "Minor", "start_junction_road_name": null, "end_junction_road_name": null, "easting": 433680, "northing": 209810, "link_length_km": null, "link_length_miles": null, "sequence": null, "ramp": null, "estimation_method": "Counted", "estimation_method_detailed": "Manual count", "direction_of_travel": "N", "pedal_cycles": 17, "two_wheeled_motor_vehicles": 12, "cars_and_taxis": 2821, "buses_and_coaches": 20, "lgvs": 456, "hgvs_2_rigid_axle": 48, "hgvs_3_rigid_axle": 5, "hgvs_4_or_more_rigid_axle": 4, "hgvs_3_or_4_articulated_axle": 3, "hgvs_5_articulated_axle": 10, "hgvs_6_articulated_axle": 4, "all_hgvs": 74, "all_motor_vehicles": 3383 }, "geometry": { "type": "Point", "coordinates": [ -1.51314034, 51.7859432 ] } },
{ "type": "Feature", "properties": { "id": 259931, "count_point_id": 931326, "year": 2008, "region_id": 9, "local_authority_id": 142, "road_name": "C", "road_category": "MCU", "road_type": "Minor", "start_junction_road_name": null, "end_junction_road_name": null, "easting": 433680, "northing": 209810, "link_length_km": null, "link_length_miles": null, "sequence": null, "ramp": null, "estimation_method": "Counted", "estimation_method_detailed": "Manual count", "direction_of_travel": "S", "pedal_cycles": 20, "two_wheeled_motor_vehicles": 12, "cars_and_taxis": 2877, "buses_and_coaches": 22, "lgvs": 404, "hgvs_2_rigid_axle": 25, "hgvs_3_rigid_axle": 6, "hgvs_4_or_more_rigid_axle": 3, "hgvs_3_or_4_articulated_axle": 3, "hgvs_5_articulated_axle": 9, "hgvs_6_articulated_axle": 2, "all_hgvs": 48, "all_motor_vehicles": 3363 }, "geometry": { "type": "Point", "coordinates": [ -1.51314034, 51.7859432 ] } }
]
}
