{
"type": "FeatureCollection",
"crs": { "type": "name", "properties": { "name": "urn:ogc:def:crs:OGC:1.3:CRS84" } },
"features": [
{ "type": "Feature", "properties": { "id": 275086, "count_point_id": 931289, "year": 2008, "region_id": 10, "local_authority_id": 117, "road_name": "C", "road_category": "MCU", "road_type": "Minor", "start_junction_road_name": null, "end_junction_road_name": null, "easting": 382370, "northing": 298730, "link_length_km": null, "link_length_miles": null, "sequence": null, "ramp": null, "estimation_method": "Counted", "estimation_method_detailed": "Manual count", "direction_of_travel": "S", "pedal_cycles": 18, "two_wheeled_motor_vehicles": 6, "cars_and_taxis": 515, "buses_and_coaches": 5, "lgvs": 78, "hgvs_2_rigid_axle": 17, "hgvs_3_rigid_axle": 2, "hgvs_4_or_more_rigid_axle": 0, "hgvs_3_or_4_articulated_axle": 1, "hgvs_5_articulated_axle": 0, "hgvs_6_articulated_axle": 0, "all_hgvs": 20, "all_motor_vehicles": 624 }, "geometry": { "type": "Point", "coordinates": [ -2.26164512, 52.58608747 ] } },
{ "type": "Feature", "properties": { "id": 275085, "count_point_id": 931289, "year": 2008, "region_id": 10, "local_authority_id": 117, "road_name": "C", "road_category": "MCU", "road_type": "Minor", "start_junction_road_name": null, "end_junction_road_name": null, "easting": 382370, "northing": 298730, "link_length_km": null, "link_length_miles": null, "sequence": null, "ramp": null, "estimation_method": "Counted", "estimation_method_detailed": "Manual count", "direction_of_travel": "N", "pedal_cycles": 9, "two_wheeled_motor_vehicles": 2, "cars_and_taxis": 469, "buses_and_coaches": 3, "lgvs": 77, "hgvs_2_rigid_axle": 18, "hgvs_3_rigid_axle": 3, "hgvs_4_or_more_rigid_axle": 0, "hgvs_3_or_4_articulated_axle": 0, "hgvs_5_articulated_axle": 0, "hgvs_6_articulated_axle": 0, "all_hgvs": 21, "all_motor_vehicles": 572 }, "geometry": { "type": "Point", "coordinates": [ -2.26164512, 52.58608747 ] } }
]
}
