{
"type": "FeatureCollection",
"crs": { "type": "name", "properties": { "name": "urn:ogc:def:crs:OGC:1.3:CRS84" } },
"features": [
{ "type": "Feature", "properties": { "id": 67374, "count_point_id": 962247, "year": 2001, "region_id": 9, "local_authority_id": 135, "road_name": "B2029", "road_category": "MB", "road_type": "Minor", "start_junction_road_name": null, "end_junction_road_name": null, "easting": 538100, "northing": 144000, "link_length_km": null, "link_length_miles": null, "sequence": null, "ramp": null, "estimation_method": "Counted", "estimation_method_detailed": "Manual count", "direction_of_travel": "N", "pedal_cycles": 17, "two_wheeled_motor_vehicles": 36, "cars_and_taxis": 3780, "buses_and_coaches": 22, "lgvs": 423, "hgvs_2_rigid_axle": 80, "hgvs_3_rigid_axle": 13, "hgvs_4_or_more_rigid_axle": 7, "hgvs_3_or_4_articulated_axle": 6, "hgvs_5_articulated_axle": 2, "hgvs_6_articulated_axle": 3, "all_hgvs": 111, "all_motor_vehicles": 4372 }, "geometry": { "type": "Point", "coordinates": [ -0.0256733, 51.17856527 ] } },
{ "type": "Feature", "properties": { "id": 48735, "count_point_id": 962247, "year": 2002, "region_id": 9, "local_authority_id": 135, "road_name": "B2029", "road_category": "MB", "road_type": "Minor", "start_junction_road_name": null, "end_junction_road_name": null, "easting": 538100, "northing": 144000, "link_length_km": null, "link_length_miles": null, "sequence": null, "ramp": null, "estimation_method": "Counted", "estimation_method_detailed": "Manual count", "direction_of_travel": "S", "pedal_cycles": 13, "two_wheeled_motor_vehicles": 44, "cars_and_taxis": 3689, "buses_and_coaches": 19, "lgvs": 443, "hgvs_2_rigid_axle": 62, "hgvs_3_rigid_axle": 7, "hgvs_4_or_more_rigid_axle": 2, "hgvs_3_or_4_articulated_axle": 0, "hgvs_5_articulated_axle": 0, "hgvs_6_articulated_axle": 2, "all_hgvs": 73, "all_motor_vehicles": 4268 }, "geometry": { "type": "Point", "coordinates": [ -0.0256733, 51.17856527 ] } },
{ "type": "Feature", "properties": { "id": 48734, "count_point_id": 962247, "year": 2002, "region_id": 9, "local_authority_id": 135, "road_name": "B2029", "road_category": "MB", "road_type": "Minor", "start_junction_road_name": null, "end_junction_road_name": null, "easting": 538100, "northing": 144000, "link_length_km": null, "link_length_miles": null, "sequence": null, "ramp": null, "estimation_method": "Counted", "estimation_method_detailed": "Manual count", "direction_of_travel": "N", "pedal_cycles": 8, "two_wheeled_motor_vehicles": 36, "cars_and_taxis": 3848, "buses_and_coaches": 18, "lgvs": 450, "hgvs_2_rigid_axle": 60, "hgvs_3_rigid_axle": 5, "hgvs_4_or_more_rigid_axle": 3, "hgvs_3_or_4_articulated_axle": 0, "hgvs_5_articulated_axle": 1, "hgvs_6_articulated_axle": 1, "all_hgvs": 70, "all_motor_vehicles": 4422 }, "geometry": { "type": "Point", "coordinates": [ -0.0256733, 51.17856527 ] } },
{ "type": "Feature", "properties": { "id": 67375, "count_point_id": 962247, "year": 2001, "region_id": 9, "local_authority_id": 135, "road_name": "B2029", "road_category": "MB", "road_type": "Minor", "start_junction_road_name": null, "end_junction_road_name": null, "easting": 538100, "northing": 144000, "link_length_km": null, "link_length_miles": null, "sequence": null, "ramp": null, "estimation_method": "Counted", "estimation_method_detailed": "Manual count", "direction_of_travel": "S", "pedal_cycles": 11, "two_wheeled_motor_vehicles": 43, "cars_and_taxis": 3717, "buses_and_coaches": 24, "lgvs": 508, "hgvs_2_rigid_axle": 79, "hgvs_3_rigid_axle": 11, "hgvs_4_or_more_rigid_axle": 6, "hgvs_3_or_4_articulated_axle": 1, "hgvs_5_articulated_axle": 5, "hgvs_6_articulated_axle": 5, "all_hgvs": 107, "all_motor_vehicles": 4399 }, "geometry": { "type": "Point", "coordinates": [ -0.0256733, 51.17856527 ] } }
]
}
