{
"type": "FeatureCollection",
"crs": { "type": "name", "properties": { "name": "urn:ogc:def:crs:OGC:1.3:CRS84" } },
"features": [
{ "type": "Feature", "properties": { "id": 39346, "count_point_id": 940289, "year": 2002, "region_id": 9, "local_authority_id": 135, "road_name": "B2130", "road_category": "MB", "road_type": "Minor", "start_junction_road_name": null, "end_junction_road_name": null, "easting": 498950, "northing": 140930, "link_length_km": null, "link_length_miles": null, "sequence": null, "ramp": null, "estimation_method": "Counted", "estimation_method_detailed": "Manual count", "direction_of_travel": "N", "pedal_cycles": 10, "two_wheeled_motor_vehicles": 23, "cars_and_taxis": 1755, "buses_and_coaches": 13, "lgvs": 219, "hgvs_2_rigid_axle": 23, "hgvs_3_rigid_axle": 2, "hgvs_4_or_more_rigid_axle": 1, "hgvs_3_or_4_articulated_axle": 2, "hgvs_5_articulated_axle": 0, "hgvs_6_articulated_axle": 1, "all_hgvs": 29, "all_motor_vehicles": 2039 }, "geometry": { "type": "Point", "coordinates": [ -0.58639193, 51.1590773 ] } },
{ "type": "Feature", "properties": { "id": 39347, "count_point_id": 940289, "year": 2002, "region_id": 9, "local_authority_id": 135, "road_name": "B2130", "road_category": "MB", "road_type": "Minor", "start_junction_road_name": null, "end_junction_road_name": null, "easting": 498950, "northing": 140930, "link_length_km": null, "link_length_miles": null, "sequence": null, "ramp": null, "estimation_method": "Counted", "estimation_method_detailed": "Manual count", "direction_of_travel": "S", "pedal_cycles": 12, "two_wheeled_motor_vehicles": 29, "cars_and_taxis": 1701, "buses_and_coaches": 14, "lgvs": 198, "hgvs_2_rigid_axle": 27, "hgvs_3_rigid_axle": 1, "hgvs_4_or_more_rigid_axle": 0, "hgvs_3_or_4_articulated_axle": 1, "hgvs_5_articulated_axle": 3, "hgvs_6_articulated_axle": 0, "all_hgvs": 32, "all_motor_vehicles": 1974 }, "geometry": { "type": "Point", "coordinates": [ -0.58639193, 51.1590773 ] } },
{ "type": "Feature", "properties": { "id": 92122, "count_point_id": 940289, "year": 2000, "region_id": 9, "local_authority_id": 135, "road_name": "B2130", "road_category": "MB", "road_type": "Minor", "start_junction_road_name": null, "end_junction_road_name": null, "easting": 498950, "northing": 140930, "link_length_km": null, "link_length_miles": null, "sequence": null, "ramp": null, "estimation_method": "Counted", "estimation_method_detailed": "Manual count", "direction_of_travel": "N", "pedal_cycles": 10, "two_wheeled_motor_vehicles": 11, "cars_and_taxis": 2108, "buses_and_coaches": 16, "lgvs": 218, "hgvs_2_rigid_axle": 31, "hgvs_3_rigid_axle": 0, "hgvs_4_or_more_rigid_axle": 0, "hgvs_3_or_4_articulated_axle": 6, "hgvs_5_articulated_axle": 1, "hgvs_6_articulated_axle": 0, "all_hgvs": 38, "all_motor_vehicles": 2391 }, "geometry": { "type": "Point", "coordinates": [ -0.58639193, 51.1590773 ] } },
{ "type": "Feature", "properties": { "id": 92123, "count_point_id": 940289, "year": 2000, "region_id": 9, "local_authority_id": 135, "road_name": "B2130", "road_category": "MB", "road_type": "Minor", "start_junction_road_name": null, "end_junction_road_name": null, "easting": 498950, "northing": 140930, "link_length_km": null, "link_length_miles": null, "sequence": null, "ramp": null, "estimation_method": "Counted", "estimation_method_detailed": "Manual count", "direction_of_travel": "S", "pedal_cycles": 7, "two_wheeled_motor_vehicles": 11, "cars_and_taxis": 2110, "buses_and_coaches": 14, "lgvs": 223, "hgvs_2_rigid_axle": 34, "hgvs_3_rigid_axle": 2, "hgvs_4_or_more_rigid_axle": 0, "hgvs_3_or_4_articulated_axle": 1, "hgvs_5_articulated_axle": 1, "hgvs_6_articulated_axle": 0, "all_hgvs": 38, "all_motor_vehicles": 2396 }, "geometry": { "type": "Point", "coordinates": [ -0.58639193, 51.1590773 ] } }
]
}
