{
"type": "FeatureCollection",
"crs": { "type": "name", "properties": { "name": "urn:ogc:def:crs:OGC:1.3:CRS84" } },
"features": [
{ "type": "Feature", "properties": { "id": 103060, "count_point_id": 997004, "year": 2000, "region_id": 10, "local_authority_id": 72, "road_name": "U", "road_category": "MCU", "road_type": "Minor", "start_junction_road_name": null, "end_junction_road_name": null, "easting": 430900, "northing": 297500, "link_length_km": null, "link_length_miles": null, "sequence": null, "ramp": null, "estimation_method": "Counted", "estimation_method_detailed": "Manual count", "direction_of_travel": "W", "pedal_cycles": 4, "two_wheeled_motor_vehicles": 0, "cars_and_taxis": 280, "buses_and_coaches": 5, "lgvs": 30, "hgvs_2_rigid_axle": 2, "hgvs_3_rigid_axle": 0, "hgvs_4_or_more_rigid_axle": 0, "hgvs_3_or_4_articulated_axle": 0, "hgvs_5_articulated_axle": 0, "hgvs_6_articulated_axle": 0, "all_hgvs": 2, "all_motor_vehicles": 317 }, "geometry": { "type": "Point", "coordinates": [ -1.54547938, 52.57444836 ] } },
{ "type": "Feature", "properties": { "id": 103059, "count_point_id": 997004, "year": 2000, "region_id": 10, "local_authority_id": 72, "road_name": "U", "road_category": "MCU", "road_type": "Minor", "start_junction_road_name": null, "end_junction_road_name": null, "easting": 430900, "northing": 297500, "link_length_km": null, "link_length_miles": null, "sequence": null, "ramp": null, "estimation_method": "Counted", "estimation_method_detailed": "Manual count", "direction_of_travel": "E", "pedal_cycles": 6, "two_wheeled_motor_vehicles": 4, "cars_and_taxis": 386, "buses_and_coaches": 5, "lgvs": 41, "hgvs_2_rigid_axle": 1, "hgvs_3_rigid_axle": 1, "hgvs_4_or_more_rigid_axle": 0, "hgvs_3_or_4_articulated_axle": 0, "hgvs_5_articulated_axle": 0, "hgvs_6_articulated_axle": 0, "all_hgvs": 2, "all_motor_vehicles": 438 }, "geometry": { "type": "Point", "coordinates": [ -1.54547938, 52.57444836 ] } },
{ "type": "Feature", "properties": { "id": 513, "count_point_id": 997004, "year": 2001, "region_id": 10, "local_authority_id": 72, "road_name": "U", "road_category": "MCU", "road_type": "Minor", "start_junction_road_name": null, "end_junction_road_name": null, "easting": 430900, "northing": 297500, "link_length_km": null, "link_length_miles": null, "sequence": null, "ramp": null, "estimation_method": "Counted", "estimation_method_detailed": "Manual count", "direction_of_travel": "S", "pedal_cycles": 8, "two_wheeled_motor_vehicles": 1, "cars_and_taxis": 328, "buses_and_coaches": 4, "lgvs": 32, "hgvs_2_rigid_axle": 2, "hgvs_3_rigid_axle": 0, "hgvs_4_or_more_rigid_axle": 0, "hgvs_3_or_4_articulated_axle": 0, "hgvs_5_articulated_axle": 0, "hgvs_6_articulated_axle": 0, "all_hgvs": 2, "all_motor_vehicles": 367 }, "geometry": { "type": "Point", "coordinates": [ -1.54547938, 52.57444836 ] } },
{ "type": "Feature", "properties": { "id": 512, "count_point_id": 997004, "year": 2001, "region_id": 10, "local_authority_id": 72, "road_name": "U", "road_category": "MCU", "road_type": "Minor", "start_junction_road_name": null, "end_junction_road_name": null, "easting": 430900, "northing": 297500, "link_length_km": null, "link_length_miles": null, "sequence": null, "ramp": null, "estimation_method": "Counted", "estimation_method_detailed": "Manual count", "direction_of_travel": "N", "pedal_cycles": 3, "two_wheeled_motor_vehicles": 3, "cars_and_taxis": 246, "buses_and_coaches": 4, "lgvs": 34, "hgvs_2_rigid_axle": 1, "hgvs_3_rigid_axle": 0, "hgvs_4_or_more_rigid_axle": 0, "hgvs_3_or_4_articulated_axle": 0, "hgvs_5_articulated_axle": 0, "hgvs_6_articulated_axle": 0, "all_hgvs": 1, "all_motor_vehicles": 288 }, "geometry": { "type": "Point", "coordinates": [ -1.54547938, 52.57444836 ] } }
]
}
