{
"type": "FeatureCollection",
"crs": { "type": "name", "properties": { "name": "urn:ogc:def:crs:OGC:1.3:CRS84" } },
"features": [
{ "type": "Feature", "properties": { "id": 259737, "count_point_id": 931126, "year": 2008, "region_id": 9, "local_authority_id": 81, "road_name": "U", "road_category": "MCU", "road_type": "Minor", "start_junction_road_name": null, "end_junction_road_name": null, "easting": 538800, "northing": 139050, "link_length_km": null, "link_length_miles": null, "sequence": null, "ramp": null, "estimation_method": "Counted", "estimation_method_detailed": "Manual count", "direction_of_travel": "S", "pedal_cycles": 27, "two_wheeled_motor_vehicles": 28, "cars_and_taxis": 3761, "buses_and_coaches": 26, "lgvs": 392, "hgvs_2_rigid_axle": 46, "hgvs_3_rigid_axle": 4, "hgvs_4_or_more_rigid_axle": 2, "hgvs_3_or_4_articulated_axle": 8, "hgvs_5_articulated_axle": 3, "hgvs_6_articulated_axle": 0, "all_hgvs": 63, "all_motor_vehicles": 4270 }, "geometry": { "type": "Point", "coordinates": [ -0.01757293, 51.13391223 ] } },
{ "type": "Feature", "properties": { "id": 259736, "count_point_id": 931126, "year": 2008, "region_id": 9, "local_authority_id": 81, "road_name": "U", "road_category": "MCU", "road_type": "Minor", "start_junction_road_name": null, "end_junction_road_name": null, "easting": 538800, "northing": 139050, "link_length_km": null, "link_length_miles": null, "sequence": null, "ramp": null, "estimation_method": "Counted", "estimation_method_detailed": "Manual count", "direction_of_travel": "N", "pedal_cycles": 38, "two_wheeled_motor_vehicles": 23, "cars_and_taxis": 3481, "buses_and_coaches": 8, "lgvs": 376, "hgvs_2_rigid_axle": 30, "hgvs_3_rigid_axle": 6, "hgvs_4_or_more_rigid_axle": 3, "hgvs_3_or_4_articulated_axle": 4, "hgvs_5_articulated_axle": 1, "hgvs_6_articulated_axle": 0, "all_hgvs": 44, "all_motor_vehicles": 3932 }, "geometry": { "type": "Point", "coordinates": [ -0.01757293, 51.13391223 ] } }
]
}
