{
"type": "FeatureCollection",
"crs": { "type": "name", "properties": { "name": "urn:ogc:def:crs:OGC:1.3:CRS84" } },
"features": [
{ "type": "Feature", "properties": { "id": 271386, "count_point_id": 931235, "year": 2009, "region_id": 10, "local_authority_id": 69, "road_name": "C", "road_category": "MCU", "road_type": "Minor", "start_junction_road_name": null, "end_junction_road_name": null, "easting": 410950, "northing": 247810, "link_length_km": null, "link_length_miles": null, "sequence": null, "ramp": null, "estimation_method": "Counted", "estimation_method_detailed": "Manual count", "direction_of_travel": "N", "pedal_cycles": 2, "two_wheeled_motor_vehicles": 8, "cars_and_taxis": 707, "buses_and_coaches": 6, "lgvs": 124, "hgvs_2_rigid_axle": 16, "hgvs_3_rigid_axle": 4, "hgvs_4_or_more_rigid_axle": 4, "hgvs_3_or_4_articulated_axle": 0, "hgvs_5_articulated_axle": 3, "hgvs_6_articulated_axle": 2, "all_hgvs": 29, "all_motor_vehicles": 874 }, "geometry": { "type": "Point", "coordinates": [ -1.84145806, 52.12849267 ] } },
{ "type": "Feature", "properties": { "id": 271387, "count_point_id": 931235, "year": 2009, "region_id": 10, "local_authority_id": 69, "road_name": "C", "road_category": "MCU", "road_type": "Minor", "start_junction_road_name": null, "end_junction_road_name": null, "easting": 410950, "northing": 247810, "link_length_km": null, "link_length_miles": null, "sequence": null, "ramp": null, "estimation_method": "Counted", "estimation_method_detailed": "Manual count", "direction_of_travel": "S", "pedal_cycles": 5, "two_wheeled_motor_vehicles": 8, "cars_and_taxis": 913, "buses_and_coaches": 4, "lgvs": 162, "hgvs_2_rigid_axle": 19, "hgvs_3_rigid_axle": 4, "hgvs_4_or_more_rigid_axle": 3, "hgvs_3_or_4_articulated_axle": 0, "hgvs_5_articulated_axle": 4, "hgvs_6_articulated_axle": 4, "all_hgvs": 34, "all_motor_vehicles": 1121 }, "geometry": { "type": "Point", "coordinates": [ -1.84145806, 52.12849267 ] } }
]
}
