{
"type": "FeatureCollection",
"crs": { "type": "name", "properties": { "name": "urn:ogc:def:crs:OGC:1.3:CRS84" } },
"features": [
{ "type": "Feature", "properties": { "id": 255023, "count_point_id": 979219, "year": 2009, "region_id": 10, "local_authority_id": 116, "road_name": "U", "road_category": "MCU", "road_type": "Minor", "start_junction_road_name": null, "end_junction_road_name": null, "easting": 350248, "northing": 314655, "link_length_km": null, "link_length_miles": null, "sequence": null, "ramp": null, "estimation_method": "Counted", "estimation_method_detailed": "Manual count", "direction_of_travel": "E", "pedal_cycles": 65, "two_wheeled_motor_vehicles": 5, "cars_and_taxis": 329, "buses_and_coaches": 6, "lgvs": 27, "hgvs_2_rigid_axle": 0, "hgvs_3_rigid_axle": 0, "hgvs_4_or_more_rigid_axle": 0, "hgvs_3_or_4_articulated_axle": 0, "hgvs_5_articulated_axle": 0, "hgvs_6_articulated_axle": 0, "all_hgvs": 0, "all_motor_vehicles": 367 }, "geometry": { "type": "Point", "coordinates": [ -2.73813338, 52.72723912 ] } },
{ "type": "Feature", "properties": { "id": 255024, "count_point_id": 979219, "year": 2009, "region_id": 10, "local_authority_id": 116, "road_name": "U", "road_category": "MCU", "road_type": "Minor", "start_junction_road_name": null, "end_junction_road_name": null, "easting": 350248, "northing": 314655, "link_length_km": null, "link_length_miles": null, "sequence": null, "ramp": null, "estimation_method": "Counted", "estimation_method_detailed": "Manual count", "direction_of_travel": "W", "pedal_cycles": 53, "two_wheeled_motor_vehicles": 5, "cars_and_taxis": 307, "buses_and_coaches": 6, "lgvs": 28, "hgvs_2_rigid_axle": 0, "hgvs_3_rigid_axle": 0, "hgvs_4_or_more_rigid_axle": 0, "hgvs_3_or_4_articulated_axle": 0, "hgvs_5_articulated_axle": 0, "hgvs_6_articulated_axle": 0, "all_hgvs": 0, "all_motor_vehicles": 346 }, "geometry": { "type": "Point", "coordinates": [ -2.73813338, 52.72723912 ] } }
]
}
