{
"type": "FeatureCollection",
"crs": { "type": "name", "properties": { "name": "urn:ogc:def:crs:OGC:1.3:CRS84" } },
"features": [
{ "type": "Feature", "properties": { "id": 42234, "count_point_id": 966215, "year": 2001, "region_id": 2, "local_authority_id": 61, "road_name": "U", "road_category": "MCU", "road_type": "Minor", "start_junction_road_name": null, "end_junction_road_name": null, "easting": 445038, "northing": 346270, "link_length_km": null, "link_length_miles": null, "sequence": null, "ramp": null, "estimation_method": "Counted", "estimation_method_detailed": "Manual count", "direction_of_travel": "S", "pedal_cycles": 12, "two_wheeled_motor_vehicles": 20, "cars_and_taxis": 558, "buses_and_coaches": 5, "lgvs": 68, "hgvs_2_rigid_axle": 10, "hgvs_3_rigid_axle": 2, "hgvs_4_or_more_rigid_axle": 0, "hgvs_3_or_4_articulated_axle": 0, "hgvs_5_articulated_axle": 0, "hgvs_6_articulated_axle": 0, "all_hgvs": 12, "all_motor_vehicles": 663 }, "geometry": { "type": "Point", "coordinates": [ -1.33017774, 53.01185169 ] } },
{ "type": "Feature", "properties": { "id": 42233, "count_point_id": 966215, "year": 2001, "region_id": 2, "local_authority_id": 61, "road_name": "U", "road_category": "MCU", "road_type": "Minor", "start_junction_road_name": null, "end_junction_road_name": null, "easting": 445038, "northing": 346270, "link_length_km": null, "link_length_miles": null, "sequence": null, "ramp": null, "estimation_method": "Counted", "estimation_method_detailed": "Manual count", "direction_of_travel": "N", "pedal_cycles": 6, "two_wheeled_motor_vehicles": 12, "cars_and_taxis": 603, "buses_and_coaches": 1, "lgvs": 68, "hgvs_2_rigid_axle": 15, "hgvs_3_rigid_axle": 1, "hgvs_4_or_more_rigid_axle": 0, "hgvs_3_or_4_articulated_axle": 0, "hgvs_5_articulated_axle": 0, "hgvs_6_articulated_axle": 0, "all_hgvs": 16, "all_motor_vehicles": 700 }, "geometry": { "type": "Point", "coordinates": [ -1.33017774, 53.01185169 ] } },
{ "type": "Feature", "properties": { "id": 256355, "count_point_id": 966215, "year": 2009, "region_id": 2, "local_authority_id": 61, "road_name": "U", "road_category": "MCU", "road_type": "Minor", "start_junction_road_name": null, "end_junction_road_name": null, "easting": 445038, "northing": 346270, "link_length_km": null, "link_length_miles": null, "sequence": null, "ramp": null, "estimation_method": "Counted", "estimation_method_detailed": "Manual count", "direction_of_travel": "N", "pedal_cycles": 3, "two_wheeled_motor_vehicles": 2, "cars_and_taxis": 117, "buses_and_coaches": 0, "lgvs": 22, "hgvs_2_rigid_axle": 0, "hgvs_3_rigid_axle": 0, "hgvs_4_or_more_rigid_axle": 0, "hgvs_3_or_4_articulated_axle": 0, "hgvs_5_articulated_axle": 0, "hgvs_6_articulated_axle": 0, "all_hgvs": 0, "all_motor_vehicles": 141 }, "geometry": { "type": "Point", "coordinates": [ -1.33017774, 53.01185169 ] } },
{ "type": "Feature", "properties": { "id": 256356, "count_point_id": 966215, "year": 2009, "region_id": 2, "local_authority_id": 61, "road_name": "U", "road_category": "MCU", "road_type": "Minor", "start_junction_road_name": null, "end_junction_road_name": null, "easting": 445038, "northing": 346270, "link_length_km": null, "link_length_miles": null, "sequence": null, "ramp": null, "estimation_method": "Counted", "estimation_method_detailed": "Manual count", "direction_of_travel": "S", "pedal_cycles": 4, "two_wheeled_motor_vehicles": 5, "cars_and_taxis": 112, "buses_and_coaches": 0, "lgvs": 22, "hgvs_2_rigid_axle": 1, "hgvs_3_rigid_axle": 0, "hgvs_4_or_more_rigid_axle": 0, "hgvs_3_or_4_articulated_axle": 0, "hgvs_5_articulated_axle": 0, "hgvs_6_articulated_axle": 0, "all_hgvs": 1, "all_motor_vehicles": 140 }, "geometry": { "type": "Point", "coordinates": [ -1.33017774, 53.01185169 ] } }
]
}
