{
"type": "FeatureCollection",
"crs": { "type": "name", "properties": { "name": "urn:ogc:def:crs:OGC:1.3:CRS84" } },
"features": [
{ "type": "Feature", "properties": { "id": 260572, "count_point_id": 900024, "year": 2008, "region_id": 7, "local_authority_id": 208, "road_name": "C", "road_category": "MCU", "road_type": "Minor", "start_junction_road_name": null, "end_junction_road_name": null, "easting": 500920, "northing": 253240, "link_length_km": null, "link_length_miles": null, "sequence": null, "ramp": null, "estimation_method": "Counted", "estimation_method_detailed": "Manual count", "direction_of_travel": "N", "pedal_cycles": 17, "two_wheeled_motor_vehicles": 12, "cars_and_taxis": 3548, "buses_and_coaches": 35, "lgvs": 223, "hgvs_2_rigid_axle": 16, "hgvs_3_rigid_axle": 1, "hgvs_4_or_more_rigid_axle": 2, "hgvs_3_or_4_articulated_axle": 1, "hgvs_5_articulated_axle": 0, "hgvs_6_articulated_axle": 0, "all_hgvs": 20, "all_motor_vehicles": 3838 }, "geometry": { "type": "Point", "coordinates": [ -0.52582918, 52.16820951 ] } },
{ "type": "Feature", "properties": { "id": 260573, "count_point_id": 900024, "year": 2008, "region_id": 7, "local_authority_id": 208, "road_name": "C", "road_category": "MCU", "road_type": "Minor", "start_junction_road_name": null, "end_junction_road_name": null, "easting": 500920, "northing": 253240, "link_length_km": null, "link_length_miles": null, "sequence": null, "ramp": null, "estimation_method": "Counted", "estimation_method_detailed": "Manual count", "direction_of_travel": "S", "pedal_cycles": 14, "two_wheeled_motor_vehicles": 20, "cars_and_taxis": 1195, "buses_and_coaches": 3, "lgvs": 235, "hgvs_2_rigid_axle": 10, "hgvs_3_rigid_axle": 3, "hgvs_4_or_more_rigid_axle": 1, "hgvs_3_or_4_articulated_axle": 0, "hgvs_5_articulated_axle": 0, "hgvs_6_articulated_axle": 1, "all_hgvs": 15, "all_motor_vehicles": 1468 }, "geometry": { "type": "Point", "coordinates": [ -0.52582918, 52.16820951 ] } },
{ "type": "Feature", "properties": { "id": 270749, "count_point_id": 900024, "year": 2009, "region_id": 7, "local_authority_id": 186, "road_name": "C", "road_category": "MCU", "road_type": "Minor", "start_junction_road_name": null, "end_junction_road_name": null, "easting": 500920, "northing": 253240, "link_length_km": null, "link_length_miles": null, "sequence": null, "ramp": null, "estimation_method": "Counted", "estimation_method_detailed": "Manual count", "direction_of_travel": "N", "pedal_cycles": 25, "two_wheeled_motor_vehicles": 8, "cars_and_taxis": 1357, "buses_and_coaches": 6, "lgvs": 155, "hgvs_2_rigid_axle": 20, "hgvs_3_rigid_axle": 0, "hgvs_4_or_more_rigid_axle": 5, "hgvs_3_or_4_articulated_axle": 0, "hgvs_5_articulated_axle": 0, "hgvs_6_articulated_axle": 0, "all_hgvs": 25, "all_motor_vehicles": 1551 }, "geometry": { "type": "Point", "coordinates": [ -0.52582918, 52.16820951 ] } },
{ "type": "Feature", "properties": { "id": 270750, "count_point_id": 900024, "year": 2009, "region_id": 7, "local_authority_id": 186, "road_name": "C", "road_category": "MCU", "road_type": "Minor", "start_junction_road_name": null, "end_junction_road_name": null, "easting": 500920, "northing": 253240, "link_length_km": null, "link_length_miles": null, "sequence": null, "ramp": null, "estimation_method": "Counted", "estimation_method_detailed": "Manual count", "direction_of_travel": "S", "pedal_cycles": 11, "two_wheeled_motor_vehicles": 17, "cars_and_taxis": 1530, "buses_and_coaches": 47, "lgvs": 163, "hgvs_2_rigid_axle": 21, "hgvs_3_rigid_axle": 0, "hgvs_4_or_more_rigid_axle": 0, "hgvs_3_or_4_articulated_axle": 0, "hgvs_5_articulated_axle": 0, "hgvs_6_articulated_axle": 0, "all_hgvs": 21, "all_motor_vehicles": 1778 }, "geometry": { "type": "Point", "coordinates": [ -0.52582918, 52.16820951 ] } }
]
}
