{
"type": "FeatureCollection",
"crs": { "type": "name", "properties": { "name": "urn:ogc:def:crs:OGC:1.3:CRS84" } },
"features": [
{ "type": "Feature", "properties": { "id": 228275, "count_point_id": 26771, "year": 2017, "region_id": 11, "local_authority_id": 102, "road_name": "A196", "road_category": "PA", "road_type": "Major", "start_junction_road_name": "A1147", "end_junction_road_name": "Woodhorn Rd", "easting": 427304, "northing": 585967, "link_length_km": 2.8, "link_length_miles": 1.74, "sequence": 30.0, "ramp": 0.0, "estimation_method": "Counted", "estimation_method_detailed": "Manual count", "direction_of_travel": "S", "pedal_cycles": 46, "two_wheeled_motor_vehicles": 53, "cars_and_taxis": 5947, "buses_and_coaches": 135, "lgvs": 867, "hgvs_2_rigid_axle": 41, "hgvs_3_rigid_axle": 10, "hgvs_4_or_more_rigid_axle": 4, "hgvs_3_or_4_articulated_axle": 3, "hgvs_5_articulated_axle": 8, "hgvs_6_articulated_axle": 6, "all_hgvs": 72, "all_motor_vehicles": 7074 }, "geometry": { "type": "Point", "coordinates": [ -1.57293197, 55.16727024 ] } },
{ "type": "Feature", "properties": { "id": 228274, "count_point_id": 26771, "year": 2017, "region_id": 11, "local_authority_id": 102, "road_name": "A196", "road_category": "PA", "road_type": "Major", "start_junction_road_name": "A1147", "end_junction_road_name": "Woodhorn Rd", "easting": 427304, "northing": 585967, "link_length_km": 2.8, "link_length_miles": 1.74, "sequence": 30.0, "ramp": 0.0, "estimation_method": "Counted", "estimation_method_detailed": "Manual count", "direction_of_travel": "N", "pedal_cycles": 43, "two_wheeled_motor_vehicles": 55, "cars_and_taxis": 5654, "buses_and_coaches": 124, "lgvs": 843, "hgvs_2_rigid_axle": 36, "hgvs_3_rigid_axle": 15, "hgvs_4_or_more_rigid_axle": 0, "hgvs_3_or_4_articulated_axle": 3, "hgvs_5_articulated_axle": 9, "hgvs_6_articulated_axle": 2, "all_hgvs": 65, "all_motor_vehicles": 6741 }, "geometry": { "type": "Point", "coordinates": [ -1.57293197, 55.16727024 ] } }
]
}
