{
"type": "FeatureCollection",
"crs": { "type": "name", "properties": { "name": "urn:ogc:def:crs:OGC:1.3:CRS84" } },
"features": [
{ "type": "Feature", "properties": { "id": 51387, "count_point_id": 16400, "year": 2001, "region_id": 6, "local_authority_id": 174, "road_name": "A40", "road_category": "PA", "road_type": "Major", "start_junction_road_name": "Edward St", "end_junction_road_name": "Cheapside", "easting": 532050, "northing": 181300, "link_length_km": 0.1, "link_length_miles": 0.06, "sequence": 1270.0, "ramp": null, "estimation_method": "Estimated", "estimation_method_detailed": "Estimated from nearby links", "direction_of_travel": "C", "pedal_cycles": 609, "two_wheeled_motor_vehicles": 2572, "cars_and_taxis": 19238, "buses_and_coaches": 290, "lgvs": 3293, "hgvs_2_rigid_axle": 500, "hgvs_3_rigid_axle": 52, "hgvs_4_or_more_rigid_axle": 8, "hgvs_3_or_4_articulated_axle": 11, "hgvs_5_articulated_axle": 6, "hgvs_6_articulated_axle": 7, "all_hgvs": 584, "all_motor_vehicles": 25977 }, "geometry": { "type": "Point", "coordinates": [ -0.09834848, 51.51520016 ] } },
{ "type": "Feature", "properties": { "id": 68672, "count_point_id": 16400, "year": 2002, "region_id": 6, "local_authority_id": 174, "road_name": "A40", "road_category": "PA", "road_type": "Major", "start_junction_road_name": "Edward St", "end_junction_road_name": "Cheapside", "easting": 532050, "northing": 181300, "link_length_km": 0.1, "link_length_miles": 0.06, "sequence": 1270.0, "ramp": null, "estimation_method": "Estimated", "estimation_method_detailed": "Estimated from nearby links", "direction_of_travel": "C", "pedal_cycles": 581, "two_wheeled_motor_vehicles": 2420, "cars_and_taxis": 17160, "buses_and_coaches": 335, "lgvs": 2980, "hgvs_2_rigid_axle": 513, "hgvs_3_rigid_axle": 58, "hgvs_4_or_more_rigid_axle": 9, "hgvs_3_or_4_articulated_axle": 9, "hgvs_5_articulated_axle": 5, "hgvs_6_articulated_axle": 7, "all_hgvs": 601, "all_motor_vehicles": 23496 }, "geometry": { "type": "Point", "coordinates": [ -0.09834848, 51.51520016 ] } }
]
}
