{
"type": "FeatureCollection",
"crs": { "type": "name", "properties": { "name": "urn:ogc:def:crs:OGC:1.3:CRS84" } },
"features": [
{ "type": "Feature", "properties": { "id": 260609, "count_point_id": 930507, "year": 2008, "region_id": 10, "local_authority_id": 155, "road_name": "U", "road_category": "MCU", "road_type": "Minor", "start_junction_road_name": null, "end_junction_road_name": null, "easting": 364670, "northing": 254650, "link_length_km": null, "link_length_miles": null, "sequence": null, "ramp": null, "estimation_method": "Counted", "estimation_method_detailed": "Manual count", "direction_of_travel": "S", "pedal_cycles": 23, "two_wheeled_motor_vehicles": 5, "cars_and_taxis": 667, "buses_and_coaches": 4, "lgvs": 87, "hgvs_2_rigid_axle": 7, "hgvs_3_rigid_axle": 0, "hgvs_4_or_more_rigid_axle": 0, "hgvs_3_or_4_articulated_axle": 1, "hgvs_5_articulated_axle": 0, "hgvs_6_articulated_axle": 0, "all_hgvs": 8, "all_motor_vehicles": 771 }, "geometry": { "type": "Point", "coordinates": [ -2.51821825, 52.18895444 ] } },
{ "type": "Feature", "properties": { "id": 260608, "count_point_id": 930507, "year": 2008, "region_id": 10, "local_authority_id": 155, "road_name": "U", "road_category": "MCU", "road_type": "Minor", "start_junction_road_name": null, "end_junction_road_name": null, "easting": 364670, "northing": 254650, "link_length_km": null, "link_length_miles": null, "sequence": null, "ramp": null, "estimation_method": "Counted", "estimation_method_detailed": "Manual count", "direction_of_travel": "N", "pedal_cycles": 20, "two_wheeled_motor_vehicles": 4, "cars_and_taxis": 494, "buses_and_coaches": 5, "lgvs": 90, "hgvs_2_rigid_axle": 1, "hgvs_3_rigid_axle": 0, "hgvs_4_or_more_rigid_axle": 0, "hgvs_3_or_4_articulated_axle": 2, "hgvs_5_articulated_axle": 0, "hgvs_6_articulated_axle": 0, "all_hgvs": 3, "all_motor_vehicles": 596 }, "geometry": { "type": "Point", "coordinates": [ -2.51821825, 52.18895444 ] } }
]
}
