{
"type": "FeatureCollection",
"crs": { "type": "name", "properties": { "name": "urn:ogc:def:crs:OGC:1.3:CRS84" } },
"features": [
{ "type": "Feature", "properties": { "id": 227697, "count_point_id": 945703, "year": 2015, "region_id": 9, "local_authority_id": 80, "road_name": "U", "road_category": "MCU", "road_type": "Minor", "start_junction_road_name": null, "end_junction_road_name": null, "easting": 569528, "northing": 161594, "link_length_km": null, "link_length_miles": null, "sequence": null, "ramp": null, "estimation_method": "Counted", "estimation_method_detailed": "Manual count", "direction_of_travel": "E", "pedal_cycles": 2, "two_wheeled_motor_vehicles": 0, "cars_and_taxis": 366, "buses_and_coaches": 24, "lgvs": 51, "hgvs_2_rigid_axle": 1, "hgvs_3_rigid_axle": 0, "hgvs_4_or_more_rigid_axle": 0, "hgvs_3_or_4_articulated_axle": 0, "hgvs_5_articulated_axle": 0, "hgvs_6_articulated_axle": 0, "all_hgvs": 1, "all_motor_vehicles": 442 }, "geometry": { "type": "Point", "coordinates": [ 0.43188208, 51.32817938 ] } },
{ "type": "Feature", "properties": { "id": 179004, "count_point_id": 945703, "year": 2014, "region_id": 9, "local_authority_id": 80, "road_name": "U", "road_category": "MCU", "road_type": "Minor", "start_junction_road_name": null, "end_junction_road_name": null, "easting": 569528, "northing": 161594, "link_length_km": null, "link_length_miles": null, "sequence": null, "ramp": null, "estimation_method": "Counted", "estimation_method_detailed": "Manual count", "direction_of_travel": "W", "pedal_cycles": 5, "two_wheeled_motor_vehicles": 5, "cars_and_taxis": 355, "buses_and_coaches": 26, "lgvs": 53, "hgvs_2_rigid_axle": 2, "hgvs_3_rigid_axle": 0, "hgvs_4_or_more_rigid_axle": 1, "hgvs_3_or_4_articulated_axle": 0, "hgvs_5_articulated_axle": 0, "hgvs_6_articulated_axle": 0, "all_hgvs": 3, "all_motor_vehicles": 442 }, "geometry": { "type": "Point", "coordinates": [ 0.43188208, 51.32817938 ] } },
{ "type": "Feature", "properties": { "id": 227698, "count_point_id": 945703, "year": 2015, "region_id": 9, "local_authority_id": 80, "road_name": "U", "road_category": "MCU", "road_type": "Minor", "start_junction_road_name": null, "end_junction_road_name": null, "easting": 569528, "northing": 161594, "link_length_km": null, "link_length_miles": null, "sequence": null, "ramp": null, "estimation_method": "Counted", "estimation_method_detailed": "Manual count", "direction_of_travel": "W", "pedal_cycles": 4, "two_wheeled_motor_vehicles": 1, "cars_and_taxis": 368, "buses_and_coaches": 27, "lgvs": 47, "hgvs_2_rigid_axle": 1, "hgvs_3_rigid_axle": 0, "hgvs_4_or_more_rigid_axle": 1, "hgvs_3_or_4_articulated_axle": 0, "hgvs_5_articulated_axle": 0, "hgvs_6_articulated_axle": 0, "all_hgvs": 2, "all_motor_vehicles": 445 }, "geometry": { "type": "Point", "coordinates": [ 0.43188208, 51.32817938 ] } },
{ "type": "Feature", "properties": { "id": 179003, "count_point_id": 945703, "year": 2014, "region_id": 9, "local_authority_id": 80, "road_name": "U", "road_category": "MCU", "road_type": "Minor", "start_junction_road_name": null, "end_junction_road_name": null, "easting": 569528, "northing": 161594, "link_length_km": null, "link_length_miles": null, "sequence": null, "ramp": null, "estimation_method": "Counted", "estimation_method_detailed": "Manual count", "direction_of_travel": "E", "pedal_cycles": 2, "two_wheeled_motor_vehicles": 2, "cars_and_taxis": 341, "buses_and_coaches": 23, "lgvs": 52, "hgvs_2_rigid_axle": 1, "hgvs_3_rigid_axle": 0, "hgvs_4_or_more_rigid_axle": 1, "hgvs_3_or_4_articulated_axle": 0, "hgvs_5_articulated_axle": 0, "hgvs_6_articulated_axle": 0, "all_hgvs": 2, "all_motor_vehicles": 420 }, "geometry": { "type": "Point", "coordinates": [ 0.43188208, 51.32817938 ] } }
]
}
