{
"type": "FeatureCollection",
"crs": { "type": "name", "properties": { "name": "urn:ogc:def:crs:OGC:1.3:CRS84" } },
"features": [
{ "type": "Feature", "properties": { "id": 169019, "count_point_id": 940780, "year": 2014, "region_id": 2, "local_authority_id": 2, "road_name": "U", "road_category": "MCU", "road_type": "Minor", "start_junction_road_name": null, "end_junction_road_name": null, "easting": 450683, "northing": 323454, "link_length_km": null, "link_length_miles": null, "sequence": null, "ramp": null, "estimation_method": "Estimated", "estimation_method_detailed": "Estimated using previous year's AADF on this link", "direction_of_travel": "C", "pedal_cycles": 0, "two_wheeled_motor_vehicles": 0, "cars_and_taxis": 36, "buses_and_coaches": 0, "lgvs": 4, "hgvs_2_rigid_axle": 0, "hgvs_3_rigid_axle": 0, "hgvs_4_or_more_rigid_axle": 0, "hgvs_3_or_4_articulated_axle": 0, "hgvs_5_articulated_axle": 0, "hgvs_6_articulated_axle": 0, "all_hgvs": 0, "all_motor_vehicles": 40 }, "geometry": { "type": "Point", "coordinates": [ -1.24960025, 52.80626603 ] } },
{ "type": "Feature", "properties": { "id": 206613, "count_point_id": 940780, "year": 2015, "region_id": 2, "local_authority_id": 2, "road_name": "U", "road_category": "MCU", "road_type": "Minor", "start_junction_road_name": null, "end_junction_road_name": null, "easting": 450683, "northing": 323454, "link_length_km": null, "link_length_miles": null, "sequence": null, "ramp": null, "estimation_method": "Estimated", "estimation_method_detailed": "Estimated using previous year's AADF on this link", "direction_of_travel": "C", "pedal_cycles": 0, "two_wheeled_motor_vehicles": 0, "cars_and_taxis": 39, "buses_and_coaches": 0, "lgvs": 4, "hgvs_2_rigid_axle": 0, "hgvs_3_rigid_axle": 0, "hgvs_4_or_more_rigid_axle": 0, "hgvs_3_or_4_articulated_axle": 0, "hgvs_5_articulated_axle": 0, "hgvs_6_articulated_axle": 0, "all_hgvs": 0, "all_motor_vehicles": 43 }, "geometry": { "type": "Point", "coordinates": [ -1.24960025, 52.80626603 ] } },
{ "type": "Feature", "properties": { "id": 246173, "count_point_id": 56351, "year": 2017, "region_id": 2, "local_authority_id": 2, "road_name": "A6006", "road_category": "PA", "road_type": "Major", "start_junction_road_name": "LA Boundary", "end_junction_road_name": "A60", "easting": 451547, "northing": 324079, "link_length_km": 8.0, "link_length_miles": 4.97, "sequence": 20.0, "ramp": 0.0, "estimation_method": "Estimated", "estimation_method_detailed": "Estimated using previous year's AADF on this link", "direction_of_travel": "E", "pedal_cycles": 5, "two_wheeled_motor_vehicles": 45, "cars_and_taxis": 3548, "buses_and_coaches": 4, "lgvs": 668, "hgvs_2_rigid_axle": 108, "hgvs_3_rigid_axle": 32, "hgvs_4_or_more_rigid_axle": 83, "hgvs_3_or_4_articulated_axle": 31, "hgvs_5_articulated_axle": 59, "hgvs_6_articulated_axle": 60, "all_hgvs": 375, "all_motor_vehicles": 4640 }, "geometry": { "type": "Point", "coordinates": [ -1.23668639, 52.81180225 ] } },
{ "type": "Feature", "properties": { "id": 246174, "count_point_id": 56351, "year": 2017, "region_id": 2, "local_authority_id": 2, "road_name": "A6006", "road_category": "PA", "road_type": "Major", "start_junction_road_name": "LA Boundary", "end_junction_road_name": "A60", "easting": 451547, "northing": 324079, "link_length_km": 8.0, "link_length_miles": 4.97, "sequence": 20.0, "ramp": 0.0, "estimation_method": "Estimated", "estimation_method_detailed": "Estimated using previous year's AADF on this link", "direction_of_travel": "W", "pedal_cycles": 2, "two_wheeled_motor_vehicles": 37, "cars_and_taxis": 3260, "buses_and_coaches": 3, "lgvs": 627, "hgvs_2_rigid_axle": 87, "hgvs_3_rigid_axle": 26, "hgvs_4_or_more_rigid_axle": 90, "hgvs_3_or_4_articulated_axle": 31, "hgvs_5_articulated_axle": 67, "hgvs_6_articulated_axle": 74, "all_hgvs": 375, "all_motor_vehicles": 4301 }, "geometry": { "type": "Point", "coordinates": [ -1.23668639, 52.81180225 ] } }
]
}
