{
"type": "FeatureCollection",
"crs": { "type": "name", "properties": { "name": "urn:ogc:def:crs:OGC:1.3:CRS84" } },
"features": [
{ "type": "Feature", "properties": { "id": 256382, "count_point_id": 931323, "year": 2009, "region_id": 9, "local_authority_id": 142, "road_name": "U", "road_category": "MCU", "road_type": "Minor", "start_junction_road_name": null, "end_junction_road_name": null, "easting": 449630, "northing": 196430, "link_length_km": null, "link_length_miles": null, "sequence": null, "ramp": null, "estimation_method": "Counted", "estimation_method_detailed": "Manual count", "direction_of_travel": "S", "pedal_cycles": 275, "two_wheeled_motor_vehicles": 17, "cars_and_taxis": 247, "buses_and_coaches": 3, "lgvs": 36, "hgvs_2_rigid_axle": 0, "hgvs_3_rigid_axle": 0, "hgvs_4_or_more_rigid_axle": 0, "hgvs_3_or_4_articulated_axle": 0, "hgvs_5_articulated_axle": 0, "hgvs_6_articulated_axle": 0, "all_hgvs": 0, "all_motor_vehicles": 303 }, "geometry": { "type": "Point", "coordinates": [ -1.28383064, 51.66446725 ] } },
{ "type": "Feature", "properties": { "id": 274374, "count_point_id": 931323, "year": 2008, "region_id": 9, "local_authority_id": 142, "road_name": "U", "road_category": "MCU", "road_type": "Minor", "start_junction_road_name": null, "end_junction_road_name": null, "easting": 449630, "northing": 196430, "link_length_km": null, "link_length_miles": null, "sequence": null, "ramp": null, "estimation_method": "Counted", "estimation_method_detailed": "Manual count", "direction_of_travel": "S", "pedal_cycles": 197, "two_wheeled_motor_vehicles": 12, "cars_and_taxis": 256, "buses_and_coaches": 4, "lgvs": 36, "hgvs_2_rigid_axle": 5, "hgvs_3_rigid_axle": 2, "hgvs_4_or_more_rigid_axle": 0, "hgvs_3_or_4_articulated_axle": 2, "hgvs_5_articulated_axle": 0, "hgvs_6_articulated_axle": 0, "all_hgvs": 9, "all_motor_vehicles": 317 }, "geometry": { "type": "Point", "coordinates": [ -1.28383064, 51.66446725 ] } },
{ "type": "Feature", "properties": { "id": 274373, "count_point_id": 931323, "year": 2008, "region_id": 9, "local_authority_id": 142, "road_name": "U", "road_category": "MCU", "road_type": "Minor", "start_junction_road_name": null, "end_junction_road_name": null, "easting": 449630, "northing": 196430, "link_length_km": null, "link_length_miles": null, "sequence": null, "ramp": null, "estimation_method": "Counted", "estimation_method_detailed": "Manual count", "direction_of_travel": "N", "pedal_cycles": 195, "two_wheeled_motor_vehicles": 20, "cars_and_taxis": 1460, "buses_and_coaches": 4, "lgvs": 147, "hgvs_2_rigid_axle": 16, "hgvs_3_rigid_axle": 0, "hgvs_4_or_more_rigid_axle": 0, "hgvs_3_or_4_articulated_axle": 0, "hgvs_5_articulated_axle": 0, "hgvs_6_articulated_axle": 0, "all_hgvs": 16, "all_motor_vehicles": 1647 }, "geometry": { "type": "Point", "coordinates": [ -1.28383064, 51.66446725 ] } },
{ "type": "Feature", "properties": { "id": 256381, "count_point_id": 931323, "year": 2009, "region_id": 9, "local_authority_id": 142, "road_name": "U", "road_category": "MCU", "road_type": "Minor", "start_junction_road_name": null, "end_junction_road_name": null, "easting": 449630, "northing": 196430, "link_length_km": null, "link_length_miles": null, "sequence": null, "ramp": null, "estimation_method": "Counted", "estimation_method_detailed": "Manual count", "direction_of_travel": "N", "pedal_cycles": 303, "two_wheeled_motor_vehicles": 49, "cars_and_taxis": 1512, "buses_and_coaches": 2, "lgvs": 164, "hgvs_2_rigid_axle": 10, "hgvs_3_rigid_axle": 1, "hgvs_4_or_more_rigid_axle": 0, "hgvs_3_or_4_articulated_axle": 1, "hgvs_5_articulated_axle": 0, "hgvs_6_articulated_axle": 0, "all_hgvs": 12, "all_motor_vehicles": 1739 }, "geometry": { "type": "Point", "coordinates": [ -1.28383064, 51.66446725 ] } }
]
}
