{
"type": "FeatureCollection",
"crs": { "type": "name", "properties": { "name": "urn:ogc:def:crs:OGC:1.3:CRS84" } },
"features": [
{ "type": "Feature", "properties": { "id": 274744, "count_point_id": 931666, "year": 2008, "region_id": 2, "local_authority_id": 99, "road_name": "U", "road_category": "MCU", "road_type": "Minor", "start_junction_road_name": null, "end_junction_road_name": null, "easting": 534130, "northing": 387410, "link_length_km": null, "link_length_miles": null, "sequence": null, "ramp": null, "estimation_method": "Counted", "estimation_method_detailed": "Manual count", "direction_of_travel": "S", "pedal_cycles": 66, "two_wheeled_motor_vehicles": 40, "cars_and_taxis": 2512, "buses_and_coaches": 13, "lgvs": 315, "hgvs_2_rigid_axle": 45, "hgvs_3_rigid_axle": 7, "hgvs_4_or_more_rigid_axle": 7, "hgvs_3_or_4_articulated_axle": 0, "hgvs_5_articulated_axle": 1, "hgvs_6_articulated_axle": 0, "all_hgvs": 60, "all_motor_vehicles": 2940 }, "geometry": { "type": "Point", "coordinates": [ 0.01435677, 53.36654496 ] } },
{ "type": "Feature", "properties": { "id": 274743, "count_point_id": 931666, "year": 2008, "region_id": 2, "local_authority_id": 99, "road_name": "U", "road_category": "MCU", "road_type": "Minor", "start_junction_road_name": null, "end_junction_road_name": null, "easting": 534130, "northing": 387410, "link_length_km": null, "link_length_miles": null, "sequence": null, "ramp": null, "estimation_method": "Counted", "estimation_method_detailed": "Manual count", "direction_of_travel": "N", "pedal_cycles": 66, "two_wheeled_motor_vehicles": 34, "cars_and_taxis": 2532, "buses_and_coaches": 28, "lgvs": 332, "hgvs_2_rigid_axle": 15, "hgvs_3_rigid_axle": 6, "hgvs_4_or_more_rigid_axle": 5, "hgvs_3_or_4_articulated_axle": 4, "hgvs_5_articulated_axle": 1, "hgvs_6_articulated_axle": 1, "all_hgvs": 32, "all_motor_vehicles": 2958 }, "geometry": { "type": "Point", "coordinates": [ 0.01435677, 53.36654496 ] } }
]
}
