{
"type": "FeatureCollection",
"crs": { "type": "name", "properties": { "name": "urn:ogc:def:crs:OGC:1.3:CRS84" } },
"features": [
{ "type": "Feature", "properties": { "id": 37006, "count_point_id": 944216, "year": 2002, "region_id": 5, "local_authority_id": 76, "road_name": "U", "road_category": "MCU", "road_type": "Minor", "start_junction_road_name": null, "end_junction_road_name": null, "easting": 347530, "northing": 438671, "link_length_km": null, "link_length_miles": null, "sequence": null, "ramp": null, "estimation_method": "Counted", "estimation_method_detailed": "Manual count", "direction_of_travel": "n", "pedal_cycles": 6, "two_wheeled_motor_vehicles": 1, "cars_and_taxis": 345, "buses_and_coaches": 2, "lgvs": 65, "hgvs_2_rigid_axle": 22, "hgvs_3_rigid_axle": 3, "hgvs_4_or_more_rigid_axle": 2, "hgvs_3_or_4_articulated_axle": 0, "hgvs_5_articulated_axle": 0, "hgvs_6_articulated_axle": 0, "all_hgvs": 27, "all_motor_vehicles": 440 }, "geometry": { "type": "Point", "coordinates": [ -2.79890667, 53.84162266 ] } },
{ "type": "Feature", "properties": { "id": 98437, "count_point_id": 944216, "year": 2000, "region_id": 5, "local_authority_id": 76, "road_name": "U", "road_category": "MCU", "road_type": "Minor", "start_junction_road_name": null, "end_junction_road_name": null, "easting": 347530, "northing": 438671, "link_length_km": null, "link_length_miles": null, "sequence": null, "ramp": null, "estimation_method": "Counted", "estimation_method_detailed": "Manual count", "direction_of_travel": "N", "pedal_cycles": 10, "two_wheeled_motor_vehicles": 7, "cars_and_taxis": 279, "buses_and_coaches": 1, "lgvs": 71, "hgvs_2_rigid_axle": 7, "hgvs_3_rigid_axle": 3, "hgvs_4_or_more_rigid_axle": 1, "hgvs_3_or_4_articulated_axle": 4, "hgvs_5_articulated_axle": 1, "hgvs_6_articulated_axle": 0, "all_hgvs": 16, "all_motor_vehicles": 374 }, "geometry": { "type": "Point", "coordinates": [ -2.79890667, 53.84162266 ] } },
{ "type": "Feature", "properties": { "id": 98438, "count_point_id": 944216, "year": 2000, "region_id": 5, "local_authority_id": 76, "road_name": "U", "road_category": "MCU", "road_type": "Minor", "start_junction_road_name": null, "end_junction_road_name": null, "easting": 347530, "northing": 438671, "link_length_km": null, "link_length_miles": null, "sequence": null, "ramp": null, "estimation_method": "Counted", "estimation_method_detailed": "Manual count", "direction_of_travel": "S", "pedal_cycles": 3, "two_wheeled_motor_vehicles": 2, "cars_and_taxis": 295, "buses_and_coaches": 2, "lgvs": 63, "hgvs_2_rigid_axle": 5, "hgvs_3_rigid_axle": 3, "hgvs_4_or_more_rigid_axle": 1, "hgvs_3_or_4_articulated_axle": 0, "hgvs_5_articulated_axle": 0, "hgvs_6_articulated_axle": 0, "all_hgvs": 9, "all_motor_vehicles": 371 }, "geometry": { "type": "Point", "coordinates": [ -2.79890667, 53.84162266 ] } },
{ "type": "Feature", "properties": { "id": 37007, "count_point_id": 944216, "year": 2002, "region_id": 5, "local_authority_id": 76, "road_name": "U", "road_category": "MCU", "road_type": "Minor", "start_junction_road_name": null, "end_junction_road_name": null, "easting": 347530, "northing": 438671, "link_length_km": null, "link_length_miles": null, "sequence": null, "ramp": null, "estimation_method": "Counted", "estimation_method_detailed": "Manual count", "direction_of_travel": "s", "pedal_cycles": 2, "two_wheeled_motor_vehicles": 2, "cars_and_taxis": 320, "buses_and_coaches": 1, "lgvs": 62, "hgvs_2_rigid_axle": 18, "hgvs_3_rigid_axle": 2, "hgvs_4_or_more_rigid_axle": 2, "hgvs_3_or_4_articulated_axle": 1, "hgvs_5_articulated_axle": 0, "hgvs_6_articulated_axle": 2, "all_hgvs": 25, "all_motor_vehicles": 410 }, "geometry": { "type": "Point", "coordinates": [ -2.79890667, 53.84162266 ] } }
]
}
