{
"type": "FeatureCollection",
"crs": { "type": "name", "properties": { "name": "urn:ogc:def:crs:OGC:1.3:CRS84" } },
"features": [
{ "type": "Feature", "properties": { "id": 37135, "count_point_id": 990493, "year": 2002, "region_id": 10, "local_authority_id": 187, "road_name": "U", "road_category": "MCU", "road_type": "Minor", "start_junction_road_name": null, "end_junction_road_name": null, "easting": 369060, "northing": 308070, "link_length_km": null, "link_length_miles": null, "sequence": null, "ramp": null, "estimation_method": "Counted", "estimation_method_detailed": "Manual count", "direction_of_travel": "E", "pedal_cycles": 7, "two_wheeled_motor_vehicles": 7, "cars_and_taxis": 1302, "buses_and_coaches": 63, "lgvs": 141, "hgvs_2_rigid_axle": 8, "hgvs_3_rigid_axle": 0, "hgvs_4_or_more_rigid_axle": 0, "hgvs_3_or_4_articulated_axle": 0, "hgvs_5_articulated_axle": 0, "hgvs_6_articulated_axle": 0, "all_hgvs": 8, "all_motor_vehicles": 1521 }, "geometry": { "type": "Point", "coordinates": [ -2.45896859, 52.66945153 ] } },
{ "type": "Feature", "properties": { "id": 37136, "count_point_id": 990493, "year": 2002, "region_id": 10, "local_authority_id": 187, "road_name": "U", "road_category": "MCU", "road_type": "Minor", "start_junction_road_name": null, "end_junction_road_name": null, "easting": 369060, "northing": 308070, "link_length_km": null, "link_length_miles": null, "sequence": null, "ramp": null, "estimation_method": "Counted", "estimation_method_detailed": "Manual count", "direction_of_travel": "W", "pedal_cycles": 9, "two_wheeled_motor_vehicles": 10, "cars_and_taxis": 1551, "buses_and_coaches": 71, "lgvs": 176, "hgvs_2_rigid_axle": 5, "hgvs_3_rigid_axle": 1, "hgvs_4_or_more_rigid_axle": 0, "hgvs_3_or_4_articulated_axle": 0, "hgvs_5_articulated_axle": 0, "hgvs_6_articulated_axle": 0, "all_hgvs": 6, "all_motor_vehicles": 1814 }, "geometry": { "type": "Point", "coordinates": [ -2.45896859, 52.66945153 ] } }
]
}
