{
"type": "FeatureCollection",
"crs": { "type": "name", "properties": { "name": "urn:ogc:def:crs:OGC:1.3:CRS84" } },
"features": [
{ "type": "Feature", "properties": { "id": 269943, "count_point_id": 930129, "year": 2009, "region_id": 5, "local_authority_id": 76, "road_name": "B5253", "road_category": "MB", "road_type": "Minor", "start_junction_road_name": null, "end_junction_road_name": null, "easting": 352780, "northing": 423720, "link_length_km": null, "link_length_miles": null, "sequence": null, "ramp": null, "estimation_method": "Counted", "estimation_method_detailed": "Manual count", "direction_of_travel": "N", "pedal_cycles": 22, "two_wheeled_motor_vehicles": 105, "cars_and_taxis": 8264, "buses_and_coaches": 39, "lgvs": 1371, "hgvs_2_rigid_axle": 271, "hgvs_3_rigid_axle": 55, "hgvs_4_or_more_rigid_axle": 51, "hgvs_3_or_4_articulated_axle": 38, "hgvs_5_articulated_axle": 30, "hgvs_6_articulated_axle": 51, "all_hgvs": 496, "all_motor_vehicles": 10275 }, "geometry": { "type": "Point", "coordinates": [ -2.71683197, 53.70775865 ] } },
{ "type": "Feature", "properties": { "id": 269944, "count_point_id": 930129, "year": 2009, "region_id": 5, "local_authority_id": 76, "road_name": "B5253", "road_category": "MB", "road_type": "Minor", "start_junction_road_name": null, "end_junction_road_name": null, "easting": 352780, "northing": 423720, "link_length_km": null, "link_length_miles": null, "sequence": null, "ramp": null, "estimation_method": "Counted", "estimation_method_detailed": "Manual count", "direction_of_travel": "S", "pedal_cycles": 25, "two_wheeled_motor_vehicles": 119, "cars_and_taxis": 8888, "buses_and_coaches": 44, "lgvs": 1382, "hgvs_2_rigid_axle": 322, "hgvs_3_rigid_axle": 62, "hgvs_4_or_more_rigid_axle": 45, "hgvs_3_or_4_articulated_axle": 27, "hgvs_5_articulated_axle": 27, "hgvs_6_articulated_axle": 55, "all_hgvs": 538, "all_motor_vehicles": 10971 }, "geometry": { "type": "Point", "coordinates": [ -2.71683197, 53.70775865 ] } },
{ "type": "Feature", "properties": { "id": 234904, "count_point_id": 28720, "year": 2017, "region_id": 5, "local_authority_id": 76, "road_name": "A582", "road_category": "PA", "road_type": "Major", "start_junction_road_name": "B5254", "end_junction_road_name": "Pope Lane", "easting": 352851, "northing": 424481, "link_length_km": 4.8, "link_length_miles": 2.98, "sequence": 20.0, "ramp": 0.0, "estimation_method": "Counted", "estimation_method_detailed": "Manual count", "direction_of_travel": "E", "pedal_cycles": 11, "two_wheeled_motor_vehicles": 70, "cars_and_taxis": 10447, "buses_and_coaches": 34, "lgvs": 1553, "hgvs_2_rigid_axle": 135, "hgvs_3_rigid_axle": 53, "hgvs_4_or_more_rigid_axle": 59, "hgvs_3_or_4_articulated_axle": 16, "hgvs_5_articulated_axle": 72, "hgvs_6_articulated_axle": 49, "all_hgvs": 384, "all_motor_vehicles": 12489 }, "geometry": { "type": "Point", "coordinates": [ -2.7158726, 53.71460449 ] } },
{ "type": "Feature", "properties": { "id": 234905, "count_point_id": 28720, "year": 2017, "region_id": 5, "local_authority_id": 76, "road_name": "A582", "road_category": "PA", "road_type": "Major", "start_junction_road_name": "B5254", "end_junction_road_name": "Pope Lane", "easting": 352851, "northing": 424481, "link_length_km": 4.8, "link_length_miles": 2.98, "sequence": 20.0, "ramp": 0.0, "estimation_method": "Counted", "estimation_method_detailed": "Manual count", "direction_of_travel": "W", "pedal_cycles": 18, "two_wheeled_motor_vehicles": 63, "cars_and_taxis": 10073, "buses_and_coaches": 35, "lgvs": 1610, "hgvs_2_rigid_axle": 142, "hgvs_3_rigid_axle": 48, "hgvs_4_or_more_rigid_axle": 50, "hgvs_3_or_4_articulated_axle": 11, "hgvs_5_articulated_axle": 80, "hgvs_6_articulated_axle": 65, "all_hgvs": 397, "all_motor_vehicles": 12178 }, "geometry": { "type": "Point", "coordinates": [ -2.7158726, 53.71460449 ] } }
]
}
