{
"type": "FeatureCollection",
"crs": { "type": "name", "properties": { "name": "urn:ogc:def:crs:OGC:1.3:CRS84" } },
"features": [
{ "type": "Feature", "properties": { "id": 270859, "count_point_id": 930774, "year": 2009, "region_id": 11, "local_authority_id": 164, "road_name": "U", "road_category": "MCU", "road_type": "Minor", "start_junction_road_name": null, "end_junction_road_name": null, "easting": 430440, "northing": 513410, "link_length_km": null, "link_length_miles": null, "sequence": null, "ramp": null, "estimation_method": "Counted", "estimation_method_detailed": "Manual count", "direction_of_travel": "E", "pedal_cycles": 22, "two_wheeled_motor_vehicles": 44, "cars_and_taxis": 2742, "buses_and_coaches": 15, "lgvs": 333, "hgvs_2_rigid_axle": 8, "hgvs_3_rigid_axle": 2, "hgvs_4_or_more_rigid_axle": 0, "hgvs_3_or_4_articulated_axle": 0, "hgvs_5_articulated_axle": 0, "hgvs_6_articulated_axle": 1, "all_hgvs": 11, "all_motor_vehicles": 3145 }, "geometry": { "type": "Point", "coordinates": [ -1.53131857, 54.51508463 ] } },
{ "type": "Feature", "properties": { "id": 270860, "count_point_id": 930774, "year": 2009, "region_id": 11, "local_authority_id": 164, "road_name": "U", "road_category": "MCU", "road_type": "Minor", "start_junction_road_name": null, "end_junction_road_name": null, "easting": 430440, "northing": 513410, "link_length_km": null, "link_length_miles": null, "sequence": null, "ramp": null, "estimation_method": "Counted", "estimation_method_detailed": "Manual count", "direction_of_travel": "W", "pedal_cycles": 45, "two_wheeled_motor_vehicles": 20, "cars_and_taxis": 2491, "buses_and_coaches": 6, "lgvs": 321, "hgvs_2_rigid_axle": 15, "hgvs_3_rigid_axle": 3, "hgvs_4_or_more_rigid_axle": 0, "hgvs_3_or_4_articulated_axle": 0, "hgvs_5_articulated_axle": 0, "hgvs_6_articulated_axle": 0, "all_hgvs": 18, "all_motor_vehicles": 2856 }, "geometry": { "type": "Point", "coordinates": [ -1.53131857, 54.51508463 ] } }
]
}
