{
"type": "FeatureCollection",
"crs": { "type": "name", "properties": { "name": "urn:ogc:def:crs:OGC:1.3:CRS84" } },
"features": [
{ "type": "Feature", "properties": { "id": 230036, "count_point_id": 36163, "year": 2017, "region_id": 2, "local_authority_id": 61, "road_name": "A6", "road_category": "PA", "road_type": "Major", "start_junction_road_name": "Waterswallows Rd, Buxton", "end_junction_road_name": "A623", "easting": 407334, "northing": 375515, "link_length_km": 5.6, "link_length_miles": 3.48, "sequence": 705.0, "ramp": 0.0, "estimation_method": "Counted", "estimation_method_detailed": "Manual count", "direction_of_travel": "S", "pedal_cycles": 27, "two_wheeled_motor_vehicles": 57, "cars_and_taxis": 4575, "buses_and_coaches": 55, "lgvs": 852, "hgvs_2_rigid_axle": 118, "hgvs_3_rigid_axle": 38, "hgvs_4_or_more_rigid_axle": 158, "hgvs_3_or_4_articulated_axle": 28, "hgvs_5_articulated_axle": 102, "hgvs_6_articulated_axle": 240, "all_hgvs": 684, "all_motor_vehicles": 6223 }, "geometry": { "type": "Point", "coordinates": [ -1.89147637, 53.27656891 ] } },
{ "type": "Feature", "properties": { "id": 230035, "count_point_id": 36163, "year": 2017, "region_id": 2, "local_authority_id": 61, "road_name": "A6", "road_category": "PA", "road_type": "Major", "start_junction_road_name": "Waterswallows Rd, Buxton", "end_junction_road_name": "A623", "easting": 407334, "northing": 375515, "link_length_km": 5.6, "link_length_miles": 3.48, "sequence": 705.0, "ramp": 0.0, "estimation_method": "Counted", "estimation_method_detailed": "Manual count", "direction_of_travel": "N", "pedal_cycles": 15, "two_wheeled_motor_vehicles": 50, "cars_and_taxis": 4659, "buses_and_coaches": 56, "lgvs": 920, "hgvs_2_rigid_axle": 112, "hgvs_3_rigid_axle": 40, "hgvs_4_or_more_rigid_axle": 192, "hgvs_3_or_4_articulated_axle": 16, "hgvs_5_articulated_axle": 164, "hgvs_6_articulated_axle": 200, "all_hgvs": 723, "all_motor_vehicles": 6407 }, "geometry": { "type": "Point", "coordinates": [ -1.89147637, 53.27656891 ] } },
{ "type": "Feature", "properties": { "id": 275562, "count_point_id": 940159, "year": 2009, "region_id": 2, "local_authority_id": 61, "road_name": "C", "road_category": "MCU", "road_type": "Minor", "start_junction_road_name": null, "end_junction_road_name": null, "easting": 409408, "northing": 376630, "link_length_km": null, "link_length_miles": null, "sequence": null, "ramp": null, "estimation_method": "Counted", "estimation_method_detailed": "Manual count", "direction_of_travel": "C", "pedal_cycles": 4, "two_wheeled_motor_vehicles": 0, "cars_and_taxis": 164, "buses_and_coaches": 1, "lgvs": 49, "hgvs_2_rigid_axle": 1, "hgvs_3_rigid_axle": 2, "hgvs_4_or_more_rigid_axle": 0, "hgvs_3_or_4_articulated_axle": 0, "hgvs_5_articulated_axle": 0, "hgvs_6_articulated_axle": 0, "all_hgvs": 3, "all_motor_vehicles": 217 }, "geometry": { "type": "Point", "coordinates": [ -1.86034133, 53.28655903 ] } },
{ "type": "Feature", "properties": { "id": 275620, "count_point_id": 940156, "year": 2008, "region_id": 2, "local_authority_id": 61, "road_name": "C", "road_category": "MCU", "road_type": "Minor", "start_junction_road_name": null, "end_junction_road_name": null, "easting": 406909, "northing": 379500, "link_length_km": null, "link_length_miles": null, "sequence": null, "ramp": null, "estimation_method": "Counted", "estimation_method_detailed": "Manual count", "direction_of_travel": "E", "pedal_cycles": 0, "two_wheeled_motor_vehicles": 2, "cars_and_taxis": 12, "buses_and_coaches": 0, "lgvs": 3, "hgvs_2_rigid_axle": 1, "hgvs_3_rigid_axle": 0, "hgvs_4_or_more_rigid_axle": 0, "hgvs_3_or_4_articulated_axle": 0, "hgvs_5_articulated_axle": 0, "hgvs_6_articulated_axle": 0, "all_hgvs": 1, "all_motor_vehicles": 18 }, "geometry": { "type": "Point", "coordinates": [ -1.89776455, 53.3123945 ] } },
{ "type": "Feature", "properties": { "id": 275621, "count_point_id": 940156, "year": 2008, "region_id": 2, "local_authority_id": 61, "road_name": "C", "road_category": "MCU", "road_type": "Minor", "start_junction_road_name": null, "end_junction_road_name": null, "easting": 406909, "northing": 379500, "link_length_km": null, "link_length_miles": null, "sequence": null, "ramp": null, "estimation_method": "Counted", "estimation_method_detailed": "Manual count", "direction_of_travel": "W", "pedal_cycles": 5, "two_wheeled_motor_vehicles": 0, "cars_and_taxis": 11, "buses_and_coaches": 0, "lgvs": 3, "hgvs_2_rigid_axle": 1, "hgvs_3_rigid_axle": 1, "hgvs_4_or_more_rigid_axle": 0, "hgvs_3_or_4_articulated_axle": 0, "hgvs_5_articulated_axle": 0, "hgvs_6_articulated_axle": 0, "all_hgvs": 2, "all_motor_vehicles": 16 }, "geometry": { "type": "Point", "coordinates": [ -1.89776455, 53.3123945 ] } }
]
}
