{
"type": "FeatureCollection",
"crs": { "type": "name", "properties": { "name": "urn:ogc:def:crs:OGC:1.3:CRS84" } },
"features": [
{ "type": "Feature", "properties": { "id": 247333, "count_point_id": 89034, "year": 2017, "region_id": 2, "local_authority_id": 99, "road_name": "A15", "road_category": "PA", "road_type": "Major", "start_junction_road_name": "A57", "end_junction_road_name": "Wolsey Way", "easting": 498984, "northing": 372470, "link_length_km": 4.2, "link_length_miles": 2.61, "sequence": 245.0, "ramp": 0.0, "estimation_method": "Counted", "estimation_method_detailed": "Manual count", "direction_of_travel": "N", "pedal_cycles": 55, "two_wheeled_motor_vehicles": 59, "cars_and_taxis": 6614, "buses_and_coaches": 35, "lgvs": 914, "hgvs_2_rigid_axle": 104, "hgvs_3_rigid_axle": 15, "hgvs_4_or_more_rigid_axle": 31, "hgvs_3_or_4_articulated_axle": 22, "hgvs_5_articulated_axle": 55, "hgvs_6_articulated_axle": 41, "all_hgvs": 267, "all_motor_vehicles": 7890 }, "geometry": { "type": "Point", "coordinates": [ -0.51827317, 53.24004163 ] } },
{ "type": "Feature", "properties": { "id": 247334, "count_point_id": 89034, "year": 2017, "region_id": 2, "local_authority_id": 99, "road_name": "A15", "road_category": "PA", "road_type": "Major", "start_junction_road_name": "A57", "end_junction_road_name": "Wolsey Way", "easting": 498984, "northing": 372470, "link_length_km": 4.2, "link_length_miles": 2.61, "sequence": 245.0, "ramp": 0.0, "estimation_method": "Counted", "estimation_method_detailed": "Manual count", "direction_of_travel": "S", "pedal_cycles": 62, "two_wheeled_motor_vehicles": 67, "cars_and_taxis": 6314, "buses_and_coaches": 48, "lgvs": 928, "hgvs_2_rigid_axle": 103, "hgvs_3_rigid_axle": 21, "hgvs_4_or_more_rigid_axle": 47, "hgvs_3_or_4_articulated_axle": 13, "hgvs_5_articulated_axle": 58, "hgvs_6_articulated_axle": 68, "all_hgvs": 310, "all_motor_vehicles": 7668 }, "geometry": { "type": "Point", "coordinates": [ -0.51827317, 53.24004163 ] } }
]
}
