{
"type": "FeatureCollection",
"crs": { "type": "name", "properties": { "name": "urn:ogc:def:crs:OGC:1.3:CRS84" } },
"features": [
{ "type": "Feature", "properties": { "id": 271412, "count_point_id": 931342, "year": 2009, "region_id": 9, "local_authority_id": 133, "road_name": "U", "road_category": "MCU", "road_type": "Minor", "start_junction_road_name": null, "end_junction_road_name": null, "easting": 582290, "northing": 110940, "link_length_km": null, "link_length_miles": null, "sequence": null, "ramp": null, "estimation_method": "Counted", "estimation_method_detailed": "Manual count", "direction_of_travel": "N", "pedal_cycles": 10, "two_wheeled_motor_vehicles": 27, "cars_and_taxis": 1059, "buses_and_coaches": 21, "lgvs": 142, "hgvs_2_rigid_axle": 15, "hgvs_3_rigid_axle": 0, "hgvs_4_or_more_rigid_axle": 1, "hgvs_3_or_4_articulated_axle": 0, "hgvs_5_articulated_axle": 0, "hgvs_6_articulated_axle": 0, "all_hgvs": 16, "all_motor_vehicles": 1265 }, "geometry": { "type": "Point", "coordinates": [ 0.5893061, 50.86922037 ] } },
{ "type": "Feature", "properties": { "id": 271413, "count_point_id": 931342, "year": 2009, "region_id": 9, "local_authority_id": 133, "road_name": "U", "road_category": "MCU", "road_type": "Minor", "start_junction_road_name": null, "end_junction_road_name": null, "easting": 582290, "northing": 110940, "link_length_km": null, "link_length_miles": null, "sequence": null, "ramp": null, "estimation_method": "Counted", "estimation_method_detailed": "Manual count", "direction_of_travel": "S", "pedal_cycles": 10, "two_wheeled_motor_vehicles": 22, "cars_and_taxis": 958, "buses_and_coaches": 22, "lgvs": 132, "hgvs_2_rigid_axle": 18, "hgvs_3_rigid_axle": 1, "hgvs_4_or_more_rigid_axle": 1, "hgvs_3_or_4_articulated_axle": 1, "hgvs_5_articulated_axle": 0, "hgvs_6_articulated_axle": 0, "all_hgvs": 21, "all_motor_vehicles": 1155 }, "geometry": { "type": "Point", "coordinates": [ 0.5893061, 50.86922037 ] } },
{ "type": "Feature", "properties": { "id": 171801, "count_point_id": 945086, "year": 2014, "region_id": 9, "local_authority_id": 133, "road_name": "U", "road_category": "MCU", "road_type": "Minor", "start_junction_road_name": null, "end_junction_road_name": null, "easting": 582514, "northing": 111778, "link_length_km": null, "link_length_miles": null, "sequence": null, "ramp": null, "estimation_method": "Estimated", "estimation_method_detailed": "Estimated using previous year's AADF on this link", "direction_of_travel": "C", "pedal_cycles": 0, "two_wheeled_motor_vehicles": 0, "cars_and_taxis": 54, "buses_and_coaches": 0, "lgvs": 2, "hgvs_2_rigid_axle": 0, "hgvs_3_rigid_axle": 0, "hgvs_4_or_more_rigid_axle": 0, "hgvs_3_or_4_articulated_axle": 0, "hgvs_5_articulated_axle": 0, "hgvs_6_articulated_axle": 0, "all_hgvs": 0, "all_motor_vehicles": 56 }, "geometry": { "type": "Point", "coordinates": [ 0.59290396, 50.87667769 ] } },
{ "type": "Feature", "properties": { "id": 206750, "count_point_id": 945086, "year": 2013, "region_id": 9, "local_authority_id": 133, "road_name": "U", "road_category": "MCU", "road_type": "Minor", "start_junction_road_name": null, "end_junction_road_name": null, "easting": 582514, "northing": 111778, "link_length_km": null, "link_length_miles": null, "sequence": null, "ramp": null, "estimation_method": "Estimated", "estimation_method_detailed": "Estimated using previous year's AADF on this link", "direction_of_travel": "C", "pedal_cycles": 0, "two_wheeled_motor_vehicles": 0, "cars_and_taxis": 53, "buses_and_coaches": 0, "lgvs": 2, "hgvs_2_rigid_axle": 0, "hgvs_3_rigid_axle": 0, "hgvs_4_or_more_rigid_axle": 0, "hgvs_3_or_4_articulated_axle": 0, "hgvs_5_articulated_axle": 0, "hgvs_6_articulated_axle": 0, "all_hgvs": 0, "all_motor_vehicles": 55 }, "geometry": { "type": "Point", "coordinates": [ 0.59290396, 50.87667769 ] } },
{ "type": "Feature", "properties": { "id": 216494, "count_point_id": 945086, "year": 2015, "region_id": 9, "local_authority_id": 133, "road_name": "U", "road_category": "MCU", "road_type": "Minor", "start_junction_road_name": null, "end_junction_road_name": null, "easting": 582514, "northing": 111778, "link_length_km": null, "link_length_miles": null, "sequence": null, "ramp": null, "estimation_method": "Estimated", "estimation_method_detailed": "Estimated using previous year's AADF on this link", "direction_of_travel": "C", "pedal_cycles": 0, "two_wheeled_motor_vehicles": 0, "cars_and_taxis": 54, "buses_and_coaches": 0, "lgvs": 2, "hgvs_2_rigid_axle": 0, "hgvs_3_rigid_axle": 0, "hgvs_4_or_more_rigid_axle": 0, "hgvs_3_or_4_articulated_axle": 0, "hgvs_5_articulated_axle": 0, "hgvs_6_articulated_axle": 0, "all_hgvs": 0, "all_motor_vehicles": 57 }, "geometry": { "type": "Point", "coordinates": [ 0.59290396, 50.87667769 ] } }
]
}
