{
"type": "FeatureCollection",
"crs": { "type": "name", "properties": { "name": "urn:ogc:def:crs:OGC:1.3:CRS84" } },
"features": [
{ "type": "Feature", "properties": { "id": 215443, "count_point_id": 942837, "year": 2015, "region_id": 6, "local_authority_id": 124, "road_name": "U", "road_category": "MCU", "road_type": "Minor", "start_junction_road_name": null, "end_junction_road_name": null, "easting": 546042, "northing": 187140, "link_length_km": null, "link_length_miles": null, "sequence": null, "ramp": null, "estimation_method": "Counted", "estimation_method_detailed": "Manual count", "direction_of_travel": "E", "pedal_cycles": 9, "two_wheeled_motor_vehicles": 1, "cars_and_taxis": 645, "buses_and_coaches": 4, "lgvs": 32, "hgvs_2_rigid_axle": 5, "hgvs_3_rigid_axle": 0, "hgvs_4_or_more_rigid_axle": 0, "hgvs_3_or_4_articulated_axle": 0, "hgvs_5_articulated_axle": 0, "hgvs_6_articulated_axle": 0, "all_hgvs": 5, "all_motor_vehicles": 687 }, "geometry": { "type": "Point", "coordinates": [ 0.10557941, 51.56423407 ] } },
{ "type": "Feature", "properties": { "id": 215444, "count_point_id": 942837, "year": 2015, "region_id": 6, "local_authority_id": 124, "road_name": "U", "road_category": "MCU", "road_type": "Minor", "start_junction_road_name": null, "end_junction_road_name": null, "easting": 546042, "northing": 187140, "link_length_km": null, "link_length_miles": null, "sequence": null, "ramp": null, "estimation_method": "Counted", "estimation_method_detailed": "Manual count", "direction_of_travel": "W", "pedal_cycles": 10, "two_wheeled_motor_vehicles": 4, "cars_and_taxis": 543, "buses_and_coaches": 1, "lgvs": 38, "hgvs_2_rigid_axle": 3, "hgvs_3_rigid_axle": 1, "hgvs_4_or_more_rigid_axle": 0, "hgvs_3_or_4_articulated_axle": 0, "hgvs_5_articulated_axle": 0, "hgvs_6_articulated_axle": 0, "all_hgvs": 4, "all_motor_vehicles": 590 }, "geometry": { "type": "Point", "coordinates": [ 0.10557941, 51.56423407 ] } },
{ "type": "Feature", "properties": { "id": 170919, "count_point_id": 942837, "year": 2014, "region_id": 6, "local_authority_id": 124, "road_name": "U", "road_category": "MCU", "road_type": "Minor", "start_junction_road_name": null, "end_junction_road_name": null, "easting": 546042, "northing": 187140, "link_length_km": null, "link_length_miles": null, "sequence": null, "ramp": null, "estimation_method": "Counted", "estimation_method_detailed": "Manual count", "direction_of_travel": "W", "pedal_cycles": 7, "two_wheeled_motor_vehicles": 1, "cars_and_taxis": 566, "buses_and_coaches": 0, "lgvs": 27, "hgvs_2_rigid_axle": 6, "hgvs_3_rigid_axle": 0, "hgvs_4_or_more_rigid_axle": 2, "hgvs_3_or_4_articulated_axle": 1, "hgvs_5_articulated_axle": 0, "hgvs_6_articulated_axle": 0, "all_hgvs": 9, "all_motor_vehicles": 603 }, "geometry": { "type": "Point", "coordinates": [ 0.10557941, 51.56423407 ] } },
{ "type": "Feature", "properties": { "id": 170918, "count_point_id": 942837, "year": 2014, "region_id": 6, "local_authority_id": 124, "road_name": "U", "road_category": "MCU", "road_type": "Minor", "start_junction_road_name": null, "end_junction_road_name": null, "easting": 546042, "northing": 187140, "link_length_km": null, "link_length_miles": null, "sequence": null, "ramp": null, "estimation_method": "Counted", "estimation_method_detailed": "Manual count", "direction_of_travel": "E", "pedal_cycles": 10, "two_wheeled_motor_vehicles": 4, "cars_and_taxis": 630, "buses_and_coaches": 0, "lgvs": 40, "hgvs_2_rigid_axle": 6, "hgvs_3_rigid_axle": 2, "hgvs_4_or_more_rigid_axle": 2, "hgvs_3_or_4_articulated_axle": 0, "hgvs_5_articulated_axle": 0, "hgvs_6_articulated_axle": 0, "all_hgvs": 10, "all_motor_vehicles": 684 }, "geometry": { "type": "Point", "coordinates": [ 0.10557941, 51.56423407 ] } }
]
}
