{
"type": "FeatureCollection",
"crs": { "type": "name", "properties": { "name": "urn:ogc:def:crs:OGC:1.3:CRS84" } },
"features": [
{ "type": "Feature", "properties": { "id": 262142, "count_point_id": 941004, "year": 2008, "region_id": 7, "local_authority_id": 97, "road_name": "C", "road_category": "MCU", "road_type": "Minor", "start_junction_road_name": null, "end_junction_road_name": null, "easting": 538055, "northing": 270910, "link_length_km": null, "link_length_miles": null, "sequence": null, "ramp": null, "estimation_method": "Counted", "estimation_method_detailed": "Manual count", "direction_of_travel": "S", "pedal_cycles": 13, "two_wheeled_motor_vehicles": 3, "cars_and_taxis": 51, "buses_and_coaches": 0, "lgvs": 7, "hgvs_2_rigid_axle": 6, "hgvs_3_rigid_axle": 1, "hgvs_4_or_more_rigid_axle": 3, "hgvs_3_or_4_articulated_axle": 7, "hgvs_5_articulated_axle": 0, "hgvs_6_articulated_axle": 0, "all_hgvs": 17, "all_motor_vehicles": 78 }, "geometry": { "type": "Point", "coordinates": [ 0.02403126, 52.31893946 ] } },
{ "type": "Feature", "properties": { "id": 262141, "count_point_id": 941004, "year": 2008, "region_id": 7, "local_authority_id": 97, "road_name": "C", "road_category": "MCU", "road_type": "Minor", "start_junction_road_name": null, "end_junction_road_name": null, "easting": 538055, "northing": 270910, "link_length_km": null, "link_length_miles": null, "sequence": null, "ramp": null, "estimation_method": "Counted", "estimation_method_detailed": "Manual count", "direction_of_travel": "N", "pedal_cycles": 14, "two_wheeled_motor_vehicles": 3, "cars_and_taxis": 54, "buses_and_coaches": 0, "lgvs": 7, "hgvs_2_rigid_axle": 5, "hgvs_3_rigid_axle": 1, "hgvs_4_or_more_rigid_axle": 1, "hgvs_3_or_4_articulated_axle": 7, "hgvs_5_articulated_axle": 0, "hgvs_6_articulated_axle": 0, "all_hgvs": 14, "all_motor_vehicles": 78 }, "geometry": { "type": "Point", "coordinates": [ 0.02403126, 52.31893946 ] } }
]
}
