{
"type": "FeatureCollection",
"crs": { "type": "name", "properties": { "name": "urn:ogc:def:crs:OGC:1.3:CRS84" } },
"features": [
{ "type": "Feature", "properties": { "id": 261615, "count_point_id": 944962, "year": 2008, "region_id": 9, "local_authority_id": 133, "road_name": "B2112", "road_category": "MB", "road_type": "Minor", "start_junction_road_name": null, "end_junction_road_name": null, "easting": 533889, "northing": 119720, "link_length_km": null, "link_length_miles": null, "sequence": null, "ramp": null, "estimation_method": "Counted", "estimation_method_detailed": "Manual count", "direction_of_travel": "S", "pedal_cycles": 19, "two_wheeled_motor_vehicles": 53, "cars_and_taxis": 5811, "buses_and_coaches": 22, "lgvs": 700, "hgvs_2_rigid_axle": 77, "hgvs_3_rigid_axle": 14, "hgvs_4_or_more_rigid_axle": 13, "hgvs_3_or_4_articulated_axle": 12, "hgvs_5_articulated_axle": 1, "hgvs_6_articulated_axle": 4, "all_hgvs": 121, "all_motor_vehicles": 6707 }, "geometry": { "type": "Point", "coordinates": [ -0.09486254, 50.9613585 ] } },
{ "type": "Feature", "properties": { "id": 261614, "count_point_id": 944962, "year": 2008, "region_id": 9, "local_authority_id": 133, "road_name": "B2112", "road_category": "MB", "road_type": "Minor", "start_junction_road_name": null, "end_junction_road_name": null, "easting": 533889, "northing": 119720, "link_length_km": null, "link_length_miles": null, "sequence": null, "ramp": null, "estimation_method": "Counted", "estimation_method_detailed": "Manual count", "direction_of_travel": "N", "pedal_cycles": 14, "two_wheeled_motor_vehicles": 61, "cars_and_taxis": 5909, "buses_and_coaches": 24, "lgvs": 717, "hgvs_2_rigid_axle": 69, "hgvs_3_rigid_axle": 13, "hgvs_4_or_more_rigid_axle": 19, "hgvs_3_or_4_articulated_axle": 16, "hgvs_5_articulated_axle": 3, "hgvs_6_articulated_axle": 1, "all_hgvs": 121, "all_motor_vehicles": 6832 }, "geometry": { "type": "Point", "coordinates": [ -0.09486254, 50.9613585 ] } }
]
}
