{
"type": "FeatureCollection",
"crs": { "type": "name", "properties": { "name": "urn:ogc:def:crs:OGC:1.3:CRS84" } },
"features": [
{ "type": "Feature", "properties": { "id": 259828, "count_point_id": 931344, "year": 2008, "region_id": 9, "local_authority_id": 133, "road_name": "U", "road_category": "MCU", "road_type": "Minor", "start_junction_road_name": null, "end_junction_road_name": null, "easting": 549150, "northing": 98900, "link_length_km": null, "link_length_miles": null, "sequence": null, "ramp": null, "estimation_method": "Counted", "estimation_method_detailed": "Manual count", "direction_of_travel": "W", "pedal_cycles": 27, "two_wheeled_motor_vehicles": 1, "cars_and_taxis": 1598, "buses_and_coaches": 21, "lgvs": 139, "hgvs_2_rigid_axle": 29, "hgvs_3_rigid_axle": 0, "hgvs_4_or_more_rigid_axle": 0, "hgvs_3_or_4_articulated_axle": 0, "hgvs_5_articulated_axle": 0, "hgvs_6_articulated_axle": 0, "all_hgvs": 29, "all_motor_vehicles": 1788 }, "geometry": { "type": "Point", "coordinates": [ 0.11381535, 50.77051893 ] } },
{ "type": "Feature", "properties": { "id": 271414, "count_point_id": 931344, "year": 2009, "region_id": 9, "local_authority_id": 133, "road_name": "U", "road_category": "MCU", "road_type": "Minor", "start_junction_road_name": null, "end_junction_road_name": null, "easting": 549150, "northing": 98900, "link_length_km": null, "link_length_miles": null, "sequence": null, "ramp": null, "estimation_method": "Counted", "estimation_method_detailed": "Manual count", "direction_of_travel": "E", "pedal_cycles": 31, "two_wheeled_motor_vehicles": 8, "cars_and_taxis": 1811, "buses_and_coaches": 6, "lgvs": 190, "hgvs_2_rigid_axle": 9, "hgvs_3_rigid_axle": 0, "hgvs_4_or_more_rigid_axle": 0, "hgvs_3_or_4_articulated_axle": 0, "hgvs_5_articulated_axle": 0, "hgvs_6_articulated_axle": 0, "all_hgvs": 9, "all_motor_vehicles": 2024 }, "geometry": { "type": "Point", "coordinates": [ 0.11381535, 50.77051893 ] } },
{ "type": "Feature", "properties": { "id": 259827, "count_point_id": 931344, "year": 2008, "region_id": 9, "local_authority_id": 133, "road_name": "U", "road_category": "MCU", "road_type": "Minor", "start_junction_road_name": null, "end_junction_road_name": null, "easting": 549150, "northing": 98900, "link_length_km": null, "link_length_miles": null, "sequence": null, "ramp": null, "estimation_method": "Counted", "estimation_method_detailed": "Manual count", "direction_of_travel": "E", "pedal_cycles": 19, "two_wheeled_motor_vehicles": 1, "cars_and_taxis": 2049, "buses_and_coaches": 7, "lgvs": 172, "hgvs_2_rigid_axle": 29, "hgvs_3_rigid_axle": 1, "hgvs_4_or_more_rigid_axle": 0, "hgvs_3_or_4_articulated_axle": 0, "hgvs_5_articulated_axle": 0, "hgvs_6_articulated_axle": 0, "all_hgvs": 30, "all_motor_vehicles": 2259 }, "geometry": { "type": "Point", "coordinates": [ 0.11381535, 50.77051893 ] } },
{ "type": "Feature", "properties": { "id": 271415, "count_point_id": 931344, "year": 2009, "region_id": 9, "local_authority_id": 133, "road_name": "U", "road_category": "MCU", "road_type": "Minor", "start_junction_road_name": null, "end_junction_road_name": null, "easting": 549150, "northing": 98900, "link_length_km": null, "link_length_miles": null, "sequence": null, "ramp": null, "estimation_method": "Counted", "estimation_method_detailed": "Manual count", "direction_of_travel": "W", "pedal_cycles": 44, "two_wheeled_motor_vehicles": 7, "cars_and_taxis": 1518, "buses_and_coaches": 22, "lgvs": 154, "hgvs_2_rigid_axle": 6, "hgvs_3_rigid_axle": 1, "hgvs_4_or_more_rigid_axle": 1, "hgvs_3_or_4_articulated_axle": 0, "hgvs_5_articulated_axle": 0, "hgvs_6_articulated_axle": 0, "all_hgvs": 8, "all_motor_vehicles": 1709 }, "geometry": { "type": "Point", "coordinates": [ 0.11381535, 50.77051893 ] } }
]
}
