{
"type": "FeatureCollection",
"crs": { "type": "name", "properties": { "name": "urn:ogc:def:crs:OGC:1.3:CRS84" } },
"features": [
{ "type": "Feature", "properties": { "id": 33769, "count_point_id": 968247, "year": 2000, "region_id": 5, "local_authority_id": 162, "road_name": "C", "road_category": "MCU", "road_type": "Minor", "start_junction_road_name": null, "end_junction_road_name": null, "easting": 391980, "northing": 409000, "link_length_km": null, "link_length_miles": null, "sequence": null, "ramp": null, "estimation_method": "Counted", "estimation_method_detailed": "Manual count", "direction_of_travel": "S", "pedal_cycles": 5, "two_wheeled_motor_vehicles": 8, "cars_and_taxis": 1982, "buses_and_coaches": 48, "lgvs": 161, "hgvs_2_rigid_axle": 9, "hgvs_3_rigid_axle": 3, "hgvs_4_or_more_rigid_axle": 0, "hgvs_3_or_4_articulated_axle": 1, "hgvs_5_articulated_axle": 0, "hgvs_6_articulated_axle": 0, "all_hgvs": 13, "all_motor_vehicles": 2212 }, "geometry": { "type": "Point", "coordinates": [ -2.12259569, 53.57753541 ] } },
{ "type": "Feature", "properties": { "id": 33768, "count_point_id": 968247, "year": 2000, "region_id": 5, "local_authority_id": 162, "road_name": "C", "road_category": "MCU", "road_type": "Minor", "start_junction_road_name": null, "end_junction_road_name": null, "easting": 391980, "northing": 409000, "link_length_km": null, "link_length_miles": null, "sequence": null, "ramp": null, "estimation_method": "Counted", "estimation_method_detailed": "Manual count", "direction_of_travel": "N", "pedal_cycles": 1, "two_wheeled_motor_vehicles": 8, "cars_and_taxis": 1803, "buses_and_coaches": 23, "lgvs": 160, "hgvs_2_rigid_axle": 9, "hgvs_3_rigid_axle": 2, "hgvs_4_or_more_rigid_axle": 0, "hgvs_3_or_4_articulated_axle": 0, "hgvs_5_articulated_axle": 1, "hgvs_6_articulated_axle": 0, "all_hgvs": 12, "all_motor_vehicles": 2006 }, "geometry": { "type": "Point", "coordinates": [ -2.12259569, 53.57753541 ] } }
]
}
