{
"type": "FeatureCollection",
"crs": { "type": "name", "properties": { "name": "urn:ogc:def:crs:OGC:1.3:CRS84" } },
"features": [
{ "type": "Feature", "properties": { "id": 276314, "count_point_id": 944101, "year": 2009, "region_id": 5, "local_authority_id": 77, "road_name": "U", "road_category": "MCU", "road_type": "Minor", "start_junction_road_name": null, "end_junction_road_name": null, "easting": 322950, "northing": 556138, "link_length_km": null, "link_length_miles": null, "sequence": null, "ramp": null, "estimation_method": "Counted", "estimation_method_detailed": "Manual count", "direction_of_travel": "C", "pedal_cycles": 8, "two_wheeled_motor_vehicles": 0, "cars_and_taxis": 110, "buses_and_coaches": 0, "lgvs": 14, "hgvs_2_rigid_axle": 0, "hgvs_3_rigid_axle": 2, "hgvs_4_or_more_rigid_axle": 0, "hgvs_3_or_4_articulated_axle": 0, "hgvs_5_articulated_axle": 0, "hgvs_6_articulated_axle": 0, "all_hgvs": 2, "all_motor_vehicles": 126 }, "geometry": { "type": "Point", "coordinates": [ -3.20285632, 54.89401433 ] } },
{ "type": "Feature", "properties": { "id": 261050, "count_point_id": 944073, "year": 2009, "region_id": 5, "local_authority_id": 77, "road_name": "C", "road_category": "MCU", "road_type": "Minor", "start_junction_road_name": null, "end_junction_road_name": null, "easting": 328898, "northing": 554596, "link_length_km": null, "link_length_miles": null, "sequence": null, "ramp": null, "estimation_method": "Counted", "estimation_method_detailed": "Manual count", "direction_of_travel": "C", "pedal_cycles": 0, "two_wheeled_motor_vehicles": 2, "cars_and_taxis": 44, "buses_and_coaches": 0, "lgvs": 37, "hgvs_2_rigid_axle": 1, "hgvs_3_rigid_axle": 0, "hgvs_4_or_more_rigid_axle": 0, "hgvs_3_or_4_articulated_axle": 0, "hgvs_5_articulated_axle": 0, "hgvs_6_articulated_axle": 0, "all_hgvs": 1, "all_motor_vehicles": 84 }, "geometry": { "type": "Point", "coordinates": [ -3.10975705, 54.8810428 ] } }
]
}
