{
"type": "FeatureCollection",
"crs": { "type": "name", "properties": { "name": "urn:ogc:def:crs:OGC:1.3:CRS84" } },
"features": [
{ "type": "Feature", "properties": { "id": 168021, "count_point_id": 941854, "year": 2014, "region_id": 7, "local_authority_id": 154, "road_name": "U", "road_category": "MCU", "road_type": "Minor", "start_junction_road_name": null, "end_junction_road_name": null, "easting": 610926, "northing": 304020, "link_length_km": null, "link_length_miles": null, "sequence": null, "ramp": null, "estimation_method": "Estimated", "estimation_method_detailed": "Estimated using previous year's AADF on this link", "direction_of_travel": "C", "pedal_cycles": 3, "two_wheeled_motor_vehicles": 1, "cars_and_taxis": 13, "buses_and_coaches": 0, "lgvs": 2, "hgvs_2_rigid_axle": 1, "hgvs_3_rigid_axle": 1, "hgvs_4_or_more_rigid_axle": 0, "hgvs_3_or_4_articulated_axle": 0, "hgvs_5_articulated_axle": 0, "hgvs_6_articulated_axle": 0, "all_hgvs": 2, "all_motor_vehicles": 18 }, "geometry": { "type": "Point", "coordinates": [ 1.11264768, 52.59302831 ] } },
{ "type": "Feature", "properties": { "id": 261714, "count_point_id": 941854, "year": 2008, "region_id": 7, "local_authority_id": 154, "road_name": "U", "road_category": "MCU", "road_type": "Minor", "start_junction_road_name": null, "end_junction_road_name": null, "easting": 610926, "northing": 304020, "link_length_km": null, "link_length_miles": null, "sequence": null, "ramp": null, "estimation_method": "Counted", "estimation_method_detailed": "Manual count", "direction_of_travel": "E", "pedal_cycles": 1, "two_wheeled_motor_vehicles": 0, "cars_and_taxis": 6, "buses_and_coaches": 0, "lgvs": 2, "hgvs_2_rigid_axle": 0, "hgvs_3_rigid_axle": 1, "hgvs_4_or_more_rigid_axle": 0, "hgvs_3_or_4_articulated_axle": 0, "hgvs_5_articulated_axle": 0, "hgvs_6_articulated_axle": 0, "all_hgvs": 1, "all_motor_vehicles": 9 }, "geometry": { "type": "Point", "coordinates": [ 1.11264768, 52.59302831 ] } },
{ "type": "Feature", "properties": { "id": 216095, "count_point_id": 941854, "year": 2015, "region_id": 7, "local_authority_id": 154, "road_name": "U", "road_category": "MCU", "road_type": "Minor", "start_junction_road_name": null, "end_junction_road_name": null, "easting": 610926, "northing": 304020, "link_length_km": null, "link_length_miles": null, "sequence": null, "ramp": null, "estimation_method": "Estimated", "estimation_method_detailed": "Estimated using previous year's AADF on this link", "direction_of_travel": "C", "pedal_cycles": 3, "two_wheeled_motor_vehicles": 1, "cars_and_taxis": 13, "buses_and_coaches": 0, "lgvs": 3, "hgvs_2_rigid_axle": 1, "hgvs_3_rigid_axle": 1, "hgvs_4_or_more_rigid_axle": 0, "hgvs_3_or_4_articulated_axle": 0, "hgvs_5_articulated_axle": 0, "hgvs_6_articulated_axle": 0, "all_hgvs": 2, "all_motor_vehicles": 19 }, "geometry": { "type": "Point", "coordinates": [ 1.11264768, 52.59302831 ] } },
{ "type": "Feature", "properties": { "id": 261715, "count_point_id": 941854, "year": 2008, "region_id": 7, "local_authority_id": 154, "road_name": "U", "road_category": "MCU", "road_type": "Minor", "start_junction_road_name": null, "end_junction_road_name": null, "easting": 610926, "northing": 304020, "link_length_km": null, "link_length_miles": null, "sequence": null, "ramp": null, "estimation_method": "Counted", "estimation_method_detailed": "Manual count", "direction_of_travel": "W", "pedal_cycles": 1, "two_wheeled_motor_vehicles": 1, "cars_and_taxis": 4, "buses_and_coaches": 0, "lgvs": 0, "hgvs_2_rigid_axle": 1, "hgvs_3_rigid_axle": 0, "hgvs_4_or_more_rigid_axle": 0, "hgvs_3_or_4_articulated_axle": 0, "hgvs_5_articulated_axle": 0, "hgvs_6_articulated_axle": 0, "all_hgvs": 1, "all_motor_vehicles": 6 }, "geometry": { "type": "Point", "coordinates": [ 1.11264768, 52.59302831 ] } }
]
}
