{
"type": "FeatureCollection",
"crs": { "type": "name", "properties": { "name": "urn:ogc:def:crs:OGC:1.3:CRS84" } },
"features": [
{ "type": "Feature", "properties": { "id": 269909, "count_point_id": 990129, "year": 2009, "region_id": 7, "local_authority_id": 123, "road_name": "B1032", "road_category": "MB", "road_type": "Minor", "start_junction_road_name": null, "end_junction_road_name": null, "easting": 618220, "northing": 215440, "link_length_km": null, "link_length_miles": null, "sequence": null, "ramp": null, "estimation_method": "Counted", "estimation_method_detailed": "Manual count", "direction_of_travel": "W", "pedal_cycles": 52, "two_wheeled_motor_vehicles": 34, "cars_and_taxis": 2685, "buses_and_coaches": 83, "lgvs": 287, "hgvs_2_rigid_axle": 28, "hgvs_3_rigid_axle": 2, "hgvs_4_or_more_rigid_axle": 0, "hgvs_3_or_4_articulated_axle": 0, "hgvs_5_articulated_axle": 0, "hgvs_6_articulated_axle": 3, "all_hgvs": 33, "all_motor_vehicles": 3122 }, "geometry": { "type": "Point", "coordinates": [ 1.16315591, 51.7950183 ] } },
{ "type": "Feature", "properties": { "id": 269908, "count_point_id": 990129, "year": 2009, "region_id": 7, "local_authority_id": 123, "road_name": "B1032", "road_category": "MB", "road_type": "Minor", "start_junction_road_name": null, "end_junction_road_name": null, "easting": 618220, "northing": 215440, "link_length_km": null, "link_length_miles": null, "sequence": null, "ramp": null, "estimation_method": "Counted", "estimation_method_detailed": "Manual count", "direction_of_travel": "E", "pedal_cycles": 42, "two_wheeled_motor_vehicles": 21, "cars_and_taxis": 2049, "buses_and_coaches": 72, "lgvs": 199, "hgvs_2_rigid_axle": 41, "hgvs_3_rigid_axle": 0, "hgvs_4_or_more_rigid_axle": 1, "hgvs_3_or_4_articulated_axle": 4, "hgvs_5_articulated_axle": 0, "hgvs_6_articulated_axle": 0, "all_hgvs": 46, "all_motor_vehicles": 2387 }, "geometry": { "type": "Point", "coordinates": [ 1.16315591, 51.7950183 ] } }
]
}
