{
"type": "FeatureCollection",
"crs": { "type": "name", "properties": { "name": "urn:ogc:def:crs:OGC:1.3:CRS84" } },
"features": [
{ "type": "Feature", "properties": { "id": 255506, "count_point_id": 930084, "year": 2009, "region_id": 7, "local_authority_id": 123, "road_name": "B1033", "road_category": "MB", "road_type": "Minor", "start_junction_road_name": null, "end_junction_road_name": null, "easting": 617400, "northing": 222800, "link_length_km": null, "link_length_miles": null, "sequence": null, "ramp": null, "estimation_method": "Counted", "estimation_method_detailed": "Manual count", "direction_of_travel": "N", "pedal_cycles": 22, "two_wheeled_motor_vehicles": 53, "cars_and_taxis": 3819, "buses_and_coaches": 43, "lgvs": 592, "hgvs_2_rigid_axle": 101, "hgvs_3_rigid_axle": 8, "hgvs_4_or_more_rigid_axle": 11, "hgvs_3_or_4_articulated_axle": 11, "hgvs_5_articulated_axle": 8, "hgvs_6_articulated_axle": 3, "all_hgvs": 142, "all_motor_vehicles": 4649 }, "geometry": { "type": "Point", "coordinates": [ 1.15590249, 51.8614105 ] } },
{ "type": "Feature", "properties": { "id": 255507, "count_point_id": 930084, "year": 2009, "region_id": 7, "local_authority_id": 123, "road_name": "B1033", "road_category": "MB", "road_type": "Minor", "start_junction_road_name": null, "end_junction_road_name": null, "easting": 617400, "northing": 222800, "link_length_km": null, "link_length_miles": null, "sequence": null, "ramp": null, "estimation_method": "Counted", "estimation_method_detailed": "Manual count", "direction_of_travel": "S", "pedal_cycles": 16, "two_wheeled_motor_vehicles": 49, "cars_and_taxis": 3868, "buses_and_coaches": 48, "lgvs": 633, "hgvs_2_rigid_axle": 104, "hgvs_3_rigid_axle": 12, "hgvs_4_or_more_rigid_axle": 10, "hgvs_3_or_4_articulated_axle": 18, "hgvs_5_articulated_axle": 9, "hgvs_6_articulated_axle": 5, "all_hgvs": 158, "all_motor_vehicles": 4756 }, "geometry": { "type": "Point", "coordinates": [ 1.15590249, 51.8614105 ] } },
{ "type": "Feature", "properties": { "id": 276475, "count_point_id": 941127, "year": 2009, "region_id": 7, "local_authority_id": 123, "road_name": "B1032", "road_category": "MB", "road_type": "Minor", "start_junction_road_name": null, "end_junction_road_name": null, "easting": 621214, "northing": 218551, "link_length_km": null, "link_length_miles": null, "sequence": null, "ramp": null, "estimation_method": "Counted", "estimation_method_detailed": "Manual count", "direction_of_travel": "C", "pedal_cycles": 20, "two_wheeled_motor_vehicles": 63, "cars_and_taxis": 5440, "buses_and_coaches": 113, "lgvs": 669, "hgvs_2_rigid_axle": 101, "hgvs_3_rigid_axle": 11, "hgvs_4_or_more_rigid_axle": 3, "hgvs_3_or_4_articulated_axle": 6, "hgvs_5_articulated_axle": 1, "hgvs_6_articulated_axle": 0, "all_hgvs": 121, "all_motor_vehicles": 6407 }, "geometry": { "type": "Point", "coordinates": [ 1.20848521, 51.82177032 ] } }
]
}
