{
"type": "FeatureCollection",
"crs": { "type": "name", "properties": { "name": "urn:ogc:def:crs:OGC:1.3:CRS84" } },
"features": [
{ "type": "Feature", "properties": { "id": 30970, "count_point_id": 36627, "year": 2000, "region_id": 2, "local_authority_id": 61, "road_name": "A61", "road_category": "TA", "road_type": "Major", "start_junction_road_name": "Queen Victoria Rd roundabout", "end_junction_road_name": "Langer Lane", "easting": 438600, "northing": 368000, "link_length_km": 3.2, "link_length_miles": 1.99, "sequence": 100.0, "ramp": null, "estimation_method": "Counted", "estimation_method_detailed": "Manual count", "direction_of_travel": "N", "pedal_cycles": 41, "two_wheeled_motor_vehicles": 98, "cars_and_taxis": 6512, "buses_and_coaches": 121, "lgvs": 745, "hgvs_2_rigid_axle": 238, "hgvs_3_rigid_axle": 27, "hgvs_4_or_more_rigid_axle": 16, "hgvs_3_or_4_articulated_axle": 14, "hgvs_5_articulated_axle": 30, "hgvs_6_articulated_axle": 13, "all_hgvs": 338, "all_motor_vehicles": 7814 }, "geometry": { "type": "Point", "coordinates": [ -1.42352261, 53.20767422 ] } },
{ "type": "Feature", "properties": { "id": 30971, "count_point_id": 36627, "year": 2000, "region_id": 2, "local_authority_id": 61, "road_name": "A61", "road_category": "TA", "road_type": "Major", "start_junction_road_name": "Queen Victoria Rd roundabout", "end_junction_road_name": "Langer Lane", "easting": 438600, "northing": 368000, "link_length_km": 3.2, "link_length_miles": 1.99, "sequence": 100.0, "ramp": null, "estimation_method": "Counted", "estimation_method_detailed": "Manual count", "direction_of_travel": "S", "pedal_cycles": 37, "two_wheeled_motor_vehicles": 95, "cars_and_taxis": 7311, "buses_and_coaches": 133, "lgvs": 893, "hgvs_2_rigid_axle": 278, "hgvs_3_rigid_axle": 23, "hgvs_4_or_more_rigid_axle": 21, "hgvs_3_or_4_articulated_axle": 31, "hgvs_5_articulated_axle": 31, "hgvs_6_articulated_axle": 21, "all_hgvs": 405, "all_motor_vehicles": 8837 }, "geometry": { "type": "Point", "coordinates": [ -1.42352261, 53.20767422 ] } }
]
}
