{
"type": "FeatureCollection",
"crs": { "type": "name", "properties": { "name": "urn:ogc:def:crs:OGC:1.3:CRS84" } },
"features": [
{ "type": "Feature", "properties": { "id": 269099, "count_point_id": 961351, "year": 2009, "region_id": 9, "local_authority_id": 65, "road_name": "C", "road_category": "MCU", "road_type": "Minor", "start_junction_road_name": null, "end_junction_road_name": null, "easting": 469100, "northing": 116000, "link_length_km": null, "link_length_miles": null, "sequence": null, "ramp": null, "estimation_method": "Counted", "estimation_method_detailed": "Manual count", "direction_of_travel": "N", "pedal_cycles": 8, "two_wheeled_motor_vehicles": 26, "cars_and_taxis": 1849, "buses_and_coaches": 2, "lgvs": 275, "hgvs_2_rigid_axle": 15, "hgvs_3_rigid_axle": 1, "hgvs_4_or_more_rigid_axle": 0, "hgvs_3_or_4_articulated_axle": 0, "hgvs_5_articulated_axle": 0, "hgvs_6_articulated_axle": 0, "all_hgvs": 16, "all_motor_vehicles": 2168 }, "geometry": { "type": "Point", "coordinates": [ -1.01791638, 50.93931417 ] } },
{ "type": "Feature", "properties": { "id": 22319, "count_point_id": 961351, "year": 2002, "region_id": 9, "local_authority_id": 65, "road_name": "C", "road_category": "MCU", "road_type": "Minor", "start_junction_road_name": null, "end_junction_road_name": null, "easting": 469100, "northing": 116000, "link_length_km": null, "link_length_miles": null, "sequence": null, "ramp": null, "estimation_method": "Counted", "estimation_method_detailed": "Manual count", "direction_of_travel": "S", "pedal_cycles": 22, "two_wheeled_motor_vehicles": 20, "cars_and_taxis": 1879, "buses_and_coaches": 11, "lgvs": 183, "hgvs_2_rigid_axle": 24, "hgvs_3_rigid_axle": 0, "hgvs_4_or_more_rigid_axle": 1, "hgvs_3_or_4_articulated_axle": 1, "hgvs_5_articulated_axle": 0, "hgvs_6_articulated_axle": 0, "all_hgvs": 26, "all_motor_vehicles": 2119 }, "geometry": { "type": "Point", "coordinates": [ -1.01791638, 50.93931417 ] } },
{ "type": "Feature", "properties": { "id": 269100, "count_point_id": 961351, "year": 2009, "region_id": 9, "local_authority_id": 65, "road_name": "C", "road_category": "MCU", "road_type": "Minor", "start_junction_road_name": null, "end_junction_road_name": null, "easting": 469100, "northing": 116000, "link_length_km": null, "link_length_miles": null, "sequence": null, "ramp": null, "estimation_method": "Counted", "estimation_method_detailed": "Manual count", "direction_of_travel": "S", "pedal_cycles": 15, "two_wheeled_motor_vehicles": 14, "cars_and_taxis": 1740, "buses_and_coaches": 2, "lgvs": 258, "hgvs_2_rigid_axle": 18, "hgvs_3_rigid_axle": 0, "hgvs_4_or_more_rigid_axle": 0, "hgvs_3_or_4_articulated_axle": 0, "hgvs_5_articulated_axle": 0, "hgvs_6_articulated_axle": 0, "all_hgvs": 18, "all_motor_vehicles": 2032 }, "geometry": { "type": "Point", "coordinates": [ -1.01791638, 50.93931417 ] } },
{ "type": "Feature", "properties": { "id": 22318, "count_point_id": 961351, "year": 2002, "region_id": 9, "local_authority_id": 65, "road_name": "C", "road_category": "MCU", "road_type": "Minor", "start_junction_road_name": null, "end_junction_road_name": null, "easting": 469100, "northing": 116000, "link_length_km": null, "link_length_miles": null, "sequence": null, "ramp": null, "estimation_method": "Counted", "estimation_method_detailed": "Manual count", "direction_of_travel": "N", "pedal_cycles": 15, "two_wheeled_motor_vehicles": 23, "cars_and_taxis": 1861, "buses_and_coaches": 7, "lgvs": 190, "hgvs_2_rigid_axle": 13, "hgvs_3_rigid_axle": 1, "hgvs_4_or_more_rigid_axle": 0, "hgvs_3_or_4_articulated_axle": 0, "hgvs_5_articulated_axle": 0, "hgvs_6_articulated_axle": 0, "all_hgvs": 14, "all_motor_vehicles": 2095 }, "geometry": { "type": "Point", "coordinates": [ -1.01791638, 50.93931417 ] } }
]
}
