{
"type": "FeatureCollection",
"crs": { "type": "name", "properties": { "name": "urn:ogc:def:crs:OGC:1.3:CRS84" } },
"features": [
{ "type": "Feature", "properties": { "id": 211477, "count_point_id": 946937, "year": 2013, "region_id": 1, "local_authority_id": 71, "road_name": "C", "road_category": "MCU", "road_type": "Minor", "start_junction_road_name": null, "end_junction_road_name": null, "easting": 263404, "northing": 122730, "link_length_km": null, "link_length_miles": null, "sequence": null, "ramp": null, "estimation_method": "Estimated", "estimation_method_detailed": "Estimated using previous year's AADF on this link", "direction_of_travel": "C", "pedal_cycles": 0, "two_wheeled_motor_vehicles": 0, "cars_and_taxis": 19, "buses_and_coaches": 0, "lgvs": 8, "hgvs_2_rigid_axle": 1, "hgvs_3_rigid_axle": 0, "hgvs_4_or_more_rigid_axle": 0, "hgvs_3_or_4_articulated_axle": 0, "hgvs_5_articulated_axle": 0, "hgvs_6_articulated_axle": 0, "all_hgvs": 1, "all_motor_vehicles": 28 }, "geometry": { "type": "Point", "coordinates": [ -3.94753565, 50.98772022 ] } },
{ "type": "Feature", "properties": { "id": 219817, "count_point_id": 946937, "year": 2015, "region_id": 1, "local_authority_id": 71, "road_name": "C", "road_category": "MCU", "road_type": "Minor", "start_junction_road_name": null, "end_junction_road_name": null, "easting": 263404, "northing": 122730, "link_length_km": null, "link_length_miles": null, "sequence": null, "ramp": null, "estimation_method": "Estimated", "estimation_method_detailed": "Estimated using previous year's AADF on this link", "direction_of_travel": "C", "pedal_cycles": 0, "two_wheeled_motor_vehicles": 0, "cars_and_taxis": 19, "buses_and_coaches": 0, "lgvs": 9, "hgvs_2_rigid_axle": 1, "hgvs_3_rigid_axle": 0, "hgvs_4_or_more_rigid_axle": 0, "hgvs_3_or_4_articulated_axle": 0, "hgvs_5_articulated_axle": 0, "hgvs_6_articulated_axle": 0, "all_hgvs": 1, "all_motor_vehicles": 29 }, "geometry": { "type": "Point", "coordinates": [ -3.94753565, 50.98772022 ] } },
{ "type": "Feature", "properties": { "id": 264186, "count_point_id": 946937, "year": 2017, "region_id": 1, "local_authority_id": 71, "road_name": "C", "road_category": "MCU", "road_type": "Minor", "start_junction_road_name": null, "end_junction_road_name": null, "easting": 263404, "northing": 122730, "link_length_km": null, "link_length_miles": null, "sequence": null, "ramp": null, "estimation_method": "Estimated", "estimation_method_detailed": "Estimated using previous year's AADF on this link", "direction_of_travel": "C", "pedal_cycles": 0, "two_wheeled_motor_vehicles": 0, "cars_and_taxis": 19, "buses_and_coaches": 0, "lgvs": 10, "hgvs_2_rigid_axle": 1, "hgvs_3_rigid_axle": 0, "hgvs_4_or_more_rigid_axle": 0, "hgvs_3_or_4_articulated_axle": 0, "hgvs_5_articulated_axle": 0, "hgvs_6_articulated_axle": 0, "all_hgvs": 1, "all_motor_vehicles": 30 }, "geometry": { "type": "Point", "coordinates": [ -3.94753565, 50.98772022 ] } },
{ "type": "Feature", "properties": { "id": 178592, "count_point_id": 946937, "year": 2014, "region_id": 1, "local_authority_id": 71, "road_name": "C", "road_category": "MCU", "road_type": "Minor", "start_junction_road_name": null, "end_junction_road_name": null, "easting": 263404, "northing": 122730, "link_length_km": null, "link_length_miles": null, "sequence": null, "ramp": null, "estimation_method": "Estimated", "estimation_method_detailed": "Estimated using previous year's AADF on this link", "direction_of_travel": "C", "pedal_cycles": 0, "two_wheeled_motor_vehicles": 0, "cars_and_taxis": 19, "buses_and_coaches": 0, "lgvs": 8, "hgvs_2_rigid_axle": 1, "hgvs_3_rigid_axle": 0, "hgvs_4_or_more_rigid_axle": 0, "hgvs_3_or_4_articulated_axle": 0, "hgvs_5_articulated_axle": 0, "hgvs_6_articulated_axle": 0, "all_hgvs": 1, "all_motor_vehicles": 28 }, "geometry": { "type": "Point", "coordinates": [ -3.94753565, 50.98772022 ] } }
]
}
