{
"type": "FeatureCollection",
"crs": { "type": "name", "properties": { "name": "urn:ogc:def:crs:OGC:1.3:CRS84" } },
"features": [
{ "type": "Feature", "properties": { "id": 55364, "count_point_id": 943015, "year": 2001, "region_id": 7, "local_authority_id": 126, "road_name": "C", "road_category": "MCU", "road_type": "Minor", "start_junction_road_name": null, "end_junction_road_name": null, "easting": 602777, "northing": 242620, "link_length_km": null, "link_length_miles": null, "sequence": null, "ramp": null, "estimation_method": "Counted", "estimation_method_detailed": "Manual count", "direction_of_travel": "S", "pedal_cycles": 91, "two_wheeled_motor_vehicles": 3, "cars_and_taxis": 848, "buses_and_coaches": 5, "lgvs": 85, "hgvs_2_rigid_axle": 3, "hgvs_3_rigid_axle": 0, "hgvs_4_or_more_rigid_axle": 0, "hgvs_3_or_4_articulated_axle": 0, "hgvs_5_articulated_axle": 0, "hgvs_6_articulated_axle": 0, "all_hgvs": 3, "all_motor_vehicles": 944 }, "geometry": { "type": "Point", "coordinates": [ 0.95553284, 52.04487257 ] } },
{ "type": "Feature", "properties": { "id": 55363, "count_point_id": 943015, "year": 2001, "region_id": 7, "local_authority_id": 126, "road_name": "C", "road_category": "MCU", "road_type": "Minor", "start_junction_road_name": null, "end_junction_road_name": null, "easting": 602777, "northing": 242620, "link_length_km": null, "link_length_miles": null, "sequence": null, "ramp": null, "estimation_method": "Counted", "estimation_method_detailed": "Manual count", "direction_of_travel": "N", "pedal_cycles": 79, "two_wheeled_motor_vehicles": 10, "cars_and_taxis": 1073, "buses_and_coaches": 6, "lgvs": 87, "hgvs_2_rigid_axle": 4, "hgvs_3_rigid_axle": 0, "hgvs_4_or_more_rigid_axle": 0, "hgvs_3_or_4_articulated_axle": 0, "hgvs_5_articulated_axle": 0, "hgvs_6_articulated_axle": 0, "all_hgvs": 4, "all_motor_vehicles": 1180 }, "geometry": { "type": "Point", "coordinates": [ 0.95553284, 52.04487257 ] } },
{ "type": "Feature", "properties": { "id": 9476, "count_point_id": 943015, "year": 2002, "region_id": 7, "local_authority_id": 126, "road_name": "C", "road_category": "MCU", "road_type": "Minor", "start_junction_road_name": null, "end_junction_road_name": null, "easting": 602777, "northing": 242620, "link_length_km": null, "link_length_miles": null, "sequence": null, "ramp": null, "estimation_method": "Counted", "estimation_method_detailed": "Manual count", "direction_of_travel": "W", "pedal_cycles": 61, "two_wheeled_motor_vehicles": 8, "cars_and_taxis": 799, "buses_and_coaches": 8, "lgvs": 92, "hgvs_2_rigid_axle": 17, "hgvs_3_rigid_axle": 0, "hgvs_4_or_more_rigid_axle": 0, "hgvs_3_or_4_articulated_axle": 0, "hgvs_5_articulated_axle": 0, "hgvs_6_articulated_axle": 0, "all_hgvs": 17, "all_motor_vehicles": 924 }, "geometry": { "type": "Point", "coordinates": [ 0.95553284, 52.04487257 ] } },
{ "type": "Feature", "properties": { "id": 9475, "count_point_id": 943015, "year": 2002, "region_id": 7, "local_authority_id": 126, "road_name": "C", "road_category": "MCU", "road_type": "Minor", "start_junction_road_name": null, "end_junction_road_name": null, "easting": 602777, "northing": 242620, "link_length_km": null, "link_length_miles": null, "sequence": null, "ramp": null, "estimation_method": "Counted", "estimation_method_detailed": "Manual count", "direction_of_travel": "E", "pedal_cycles": 59, "two_wheeled_motor_vehicles": 6, "cars_and_taxis": 992, "buses_and_coaches": 6, "lgvs": 97, "hgvs_2_rigid_axle": 13, "hgvs_3_rigid_axle": 0, "hgvs_4_or_more_rigid_axle": 0, "hgvs_3_or_4_articulated_axle": 1, "hgvs_5_articulated_axle": 0, "hgvs_6_articulated_axle": 0, "all_hgvs": 14, "all_motor_vehicles": 1115 }, "geometry": { "type": "Point", "coordinates": [ 0.95553284, 52.04487257 ] } }
]
}
