{
"type": "FeatureCollection",
"crs": { "type": "name", "properties": { "name": "urn:ogc:def:crs:OGC:1.3:CRS84" } },
"features": [
{ "type": "Feature", "properties": { "id": 37937, "count_point_id": 966614, "year": 2002, "region_id": 2, "local_authority_id": 98, "road_name": "U", "road_category": "MCU", "road_type": "Minor", "start_junction_road_name": null, "end_junction_road_name": null, "easting": 484716, "northing": 308973, "link_length_km": null, "link_length_miles": null, "sequence": null, "ramp": null, "estimation_method": "Counted", "estimation_method_detailed": "Manual count", "direction_of_travel": "W", "pedal_cycles": 3, "two_wheeled_motor_vehicles": 5, "cars_and_taxis": 382, "buses_and_coaches": 1, "lgvs": 39, "hgvs_2_rigid_axle": 11, "hgvs_3_rigid_axle": 0, "hgvs_4_or_more_rigid_axle": 0, "hgvs_3_or_4_articulated_axle": 0, "hgvs_5_articulated_axle": 1, "hgvs_6_articulated_axle": 0, "all_hgvs": 12, "all_motor_vehicles": 439 }, "geometry": { "type": "Point", "coordinates": [ -0.74858644, 52.67185543 ] } },
{ "type": "Feature", "properties": { "id": 37936, "count_point_id": 966614, "year": 2002, "region_id": 2, "local_authority_id": 98, "road_name": "U", "road_category": "MCU", "road_type": "Minor", "start_junction_road_name": null, "end_junction_road_name": null, "easting": 484716, "northing": 308973, "link_length_km": null, "link_length_miles": null, "sequence": null, "ramp": null, "estimation_method": "Counted", "estimation_method_detailed": "Manual count", "direction_of_travel": "E", "pedal_cycles": 12, "two_wheeled_motor_vehicles": 3, "cars_and_taxis": 356, "buses_and_coaches": 1, "lgvs": 34, "hgvs_2_rigid_axle": 10, "hgvs_3_rigid_axle": 1, "hgvs_4_or_more_rigid_axle": 0, "hgvs_3_or_4_articulated_axle": 0, "hgvs_5_articulated_axle": 0, "hgvs_6_articulated_axle": 0, "all_hgvs": 11, "all_motor_vehicles": 405 }, "geometry": { "type": "Point", "coordinates": [ -0.74858644, 52.67185543 ] } },
{ "type": "Feature", "properties": { "id": 86728, "count_point_id": 966614, "year": 2000, "region_id": 2, "local_authority_id": 98, "road_name": "U", "road_category": "MCU", "road_type": "Minor", "start_junction_road_name": null, "end_junction_road_name": null, "easting": 484716, "northing": 308973, "link_length_km": null, "link_length_miles": null, "sequence": null, "ramp": null, "estimation_method": "Counted", "estimation_method_detailed": "Manual count", "direction_of_travel": "W", "pedal_cycles": 6, "two_wheeled_motor_vehicles": 2, "cars_and_taxis": 419, "buses_and_coaches": 3, "lgvs": 41, "hgvs_2_rigid_axle": 9, "hgvs_3_rigid_axle": 0, "hgvs_4_or_more_rigid_axle": 0, "hgvs_3_or_4_articulated_axle": 1, "hgvs_5_articulated_axle": 0, "hgvs_6_articulated_axle": 0, "all_hgvs": 10, "all_motor_vehicles": 475 }, "geometry": { "type": "Point", "coordinates": [ -0.74858644, 52.67185543 ] } },
{ "type": "Feature", "properties": { "id": 86727, "count_point_id": 966614, "year": 2000, "region_id": 2, "local_authority_id": 98, "road_name": "U", "road_category": "MCU", "road_type": "Minor", "start_junction_road_name": null, "end_junction_road_name": null, "easting": 484716, "northing": 308973, "link_length_km": null, "link_length_miles": null, "sequence": null, "ramp": null, "estimation_method": "Counted", "estimation_method_detailed": "Manual count", "direction_of_travel": "E", "pedal_cycles": 10, "two_wheeled_motor_vehicles": 1, "cars_and_taxis": 335, "buses_and_coaches": 5, "lgvs": 40, "hgvs_2_rigid_axle": 6, "hgvs_3_rigid_axle": 0, "hgvs_4_or_more_rigid_axle": 0, "hgvs_3_or_4_articulated_axle": 0, "hgvs_5_articulated_axle": 0, "hgvs_6_articulated_axle": 0, "all_hgvs": 6, "all_motor_vehicles": 387 }, "geometry": { "type": "Point", "coordinates": [ -0.74858644, 52.67185543 ] } }
]
}
