{
"type": "FeatureCollection",
"crs": { "type": "name", "properties": { "name": "urn:ogc:def:crs:OGC:1.3:CRS84" } },
"features": [
{ "type": "Feature", "properties": { "id": 50332, "count_point_id": 943377, "year": 2002, "region_id": 9, "local_authority_id": 80, "road_name": "U", "road_category": "MCU", "road_type": "Minor", "start_junction_road_name": null, "end_junction_road_name": null, "easting": 620779, "northing": 167445, "link_length_km": null, "link_length_miles": null, "sequence": null, "ramp": null, "estimation_method": "Counted", "estimation_method_detailed": "Manual count", "direction_of_travel": "S", "pedal_cycles": 7, "two_wheeled_motor_vehicles": 22, "cars_and_taxis": 1624, "buses_and_coaches": 17, "lgvs": 259, "hgvs_2_rigid_axle": 42, "hgvs_3_rigid_axle": 13, "hgvs_4_or_more_rigid_axle": 66, "hgvs_3_or_4_articulated_axle": 10, "hgvs_5_articulated_axle": 1, "hgvs_6_articulated_axle": 0, "all_hgvs": 132, "all_motor_vehicles": 2054 }, "geometry": { "type": "Point", "coordinates": [ 1.17005601, 51.36314267 ] } },
{ "type": "Feature", "properties": { "id": 110179, "count_point_id": 943377, "year": 2000, "region_id": 9, "local_authority_id": 80, "road_name": "U", "road_category": "MCU", "road_type": "Minor", "start_junction_road_name": null, "end_junction_road_name": null, "easting": 620779, "northing": 167445, "link_length_km": null, "link_length_miles": null, "sequence": null, "ramp": null, "estimation_method": "Counted", "estimation_method_detailed": "Manual count", "direction_of_travel": "N", "pedal_cycles": 13, "two_wheeled_motor_vehicles": 27, "cars_and_taxis": 1096, "buses_and_coaches": 30, "lgvs": 208, "hgvs_2_rigid_axle": 29, "hgvs_3_rigid_axle": 1, "hgvs_4_or_more_rigid_axle": 0, "hgvs_3_or_4_articulated_axle": 0, "hgvs_5_articulated_axle": 3, "hgvs_6_articulated_axle": 0, "all_hgvs": 33, "all_motor_vehicles": 1394 }, "geometry": { "type": "Point", "coordinates": [ 1.17005601, 51.36314267 ] } },
{ "type": "Feature", "properties": { "id": 110180, "count_point_id": 943377, "year": 2000, "region_id": 9, "local_authority_id": 80, "road_name": "U", "road_category": "MCU", "road_type": "Minor", "start_junction_road_name": null, "end_junction_road_name": null, "easting": 620779, "northing": 167445, "link_length_km": null, "link_length_miles": null, "sequence": null, "ramp": null, "estimation_method": "Counted", "estimation_method_detailed": "Manual count", "direction_of_travel": "S", "pedal_cycles": 13, "two_wheeled_motor_vehicles": 10, "cars_and_taxis": 1170, "buses_and_coaches": 28, "lgvs": 187, "hgvs_2_rigid_axle": 25, "hgvs_3_rigid_axle": 2, "hgvs_4_or_more_rigid_axle": 0, "hgvs_3_or_4_articulated_axle": 1, "hgvs_5_articulated_axle": 3, "hgvs_6_articulated_axle": 1, "all_hgvs": 32, "all_motor_vehicles": 1427 }, "geometry": { "type": "Point", "coordinates": [ 1.17005601, 51.36314267 ] } },
{ "type": "Feature", "properties": { "id": 50331, "count_point_id": 943377, "year": 2002, "region_id": 9, "local_authority_id": 80, "road_name": "U", "road_category": "MCU", "road_type": "Minor", "start_junction_road_name": null, "end_junction_road_name": null, "easting": 620779, "northing": 167445, "link_length_km": null, "link_length_miles": null, "sequence": null, "ramp": null, "estimation_method": "Counted", "estimation_method_detailed": "Manual count", "direction_of_travel": "N", "pedal_cycles": 8, "two_wheeled_motor_vehicles": 19, "cars_and_taxis": 1402, "buses_and_coaches": 22, "lgvs": 235, "hgvs_2_rigid_axle": 52, "hgvs_3_rigid_axle": 15, "hgvs_4_or_more_rigid_axle": 63, "hgvs_3_or_4_articulated_axle": 4, "hgvs_5_articulated_axle": 1, "hgvs_6_articulated_axle": 0, "all_hgvs": 135, "all_motor_vehicles": 1813 }, "geometry": { "type": "Point", "coordinates": [ 1.17005601, 51.36314267 ] } }
]
}
