{
"type": "FeatureCollection",
"crs": { "type": "name", "properties": { "name": "urn:ogc:def:crs:OGC:1.3:CRS84" } },
"features": [
{ "type": "Feature", "properties": { "id": 89908, "count_point_id": 990814, "year": 2000, "region_id": 5, "local_authority_id": 192, "road_name": "U", "road_category": "MCU", "road_type": "Minor", "start_junction_road_name": null, "end_junction_road_name": null, "easting": 330370, "northing": 400160, "link_length_km": null, "link_length_miles": null, "sequence": null, "ramp": null, "estimation_method": "Counted", "estimation_method_detailed": "Manual count", "direction_of_travel": "N", "pedal_cycles": 16, "two_wheeled_motor_vehicles": 14, "cars_and_taxis": 426, "buses_and_coaches": 0, "lgvs": 35, "hgvs_2_rigid_axle": 2, "hgvs_3_rigid_axle": 0, "hgvs_4_or_more_rigid_axle": 0, "hgvs_3_or_4_articulated_axle": 0, "hgvs_5_articulated_axle": 0, "hgvs_6_articulated_axle": 0, "all_hgvs": 2, "all_motor_vehicles": 477 }, "geometry": { "type": "Point", "coordinates": [ -3.05100626, 53.49351856 ] } },
{ "type": "Feature", "properties": { "id": 37041, "count_point_id": 990814, "year": 2002, "region_id": 5, "local_authority_id": 192, "road_name": "U", "road_category": "MCU", "road_type": "Minor", "start_junction_road_name": null, "end_junction_road_name": null, "easting": 330370, "northing": 400160, "link_length_km": null, "link_length_miles": null, "sequence": null, "ramp": null, "estimation_method": "Counted", "estimation_method_detailed": "Manual count", "direction_of_travel": "N", "pedal_cycles": 23, "two_wheeled_motor_vehicles": 1, "cars_and_taxis": 406, "buses_and_coaches": 2, "lgvs": 32, "hgvs_2_rigid_axle": 2, "hgvs_3_rigid_axle": 2, "hgvs_4_or_more_rigid_axle": 0, "hgvs_3_or_4_articulated_axle": 0, "hgvs_5_articulated_axle": 0, "hgvs_6_articulated_axle": 0, "all_hgvs": 4, "all_motor_vehicles": 445 }, "geometry": { "type": "Point", "coordinates": [ -3.05100626, 53.49351856 ] } },
{ "type": "Feature", "properties": { "id": 89909, "count_point_id": 990814, "year": 2000, "region_id": 5, "local_authority_id": 192, "road_name": "U", "road_category": "MCU", "road_type": "Minor", "start_junction_road_name": null, "end_junction_road_name": null, "easting": 330370, "northing": 400160, "link_length_km": null, "link_length_miles": null, "sequence": null, "ramp": null, "estimation_method": "Counted", "estimation_method_detailed": "Manual count", "direction_of_travel": "S", "pedal_cycles": 11, "two_wheeled_motor_vehicles": 0, "cars_and_taxis": 385, "buses_and_coaches": 0, "lgvs": 23, "hgvs_2_rigid_axle": 0, "hgvs_3_rigid_axle": 0, "hgvs_4_or_more_rigid_axle": 0, "hgvs_3_or_4_articulated_axle": 0, "hgvs_5_articulated_axle": 0, "hgvs_6_articulated_axle": 0, "all_hgvs": 0, "all_motor_vehicles": 408 }, "geometry": { "type": "Point", "coordinates": [ -3.05100626, 53.49351856 ] } },
{ "type": "Feature", "properties": { "id": 37042, "count_point_id": 990814, "year": 2002, "region_id": 5, "local_authority_id": 192, "road_name": "U", "road_category": "MCU", "road_type": "Minor", "start_junction_road_name": null, "end_junction_road_name": null, "easting": 330370, "northing": 400160, "link_length_km": null, "link_length_miles": null, "sequence": null, "ramp": null, "estimation_method": "Counted", "estimation_method_detailed": "Manual count", "direction_of_travel": "S", "pedal_cycles": 19, "two_wheeled_motor_vehicles": 0, "cars_and_taxis": 366, "buses_and_coaches": 1, "lgvs": 17, "hgvs_2_rigid_axle": 4, "hgvs_3_rigid_axle": 0, "hgvs_4_or_more_rigid_axle": 0, "hgvs_3_or_4_articulated_axle": 0, "hgvs_5_articulated_axle": 0, "hgvs_6_articulated_axle": 0, "all_hgvs": 4, "all_motor_vehicles": 388 }, "geometry": { "type": "Point", "coordinates": [ -3.05100626, 53.49351856 ] } }
]
}
