{
"type": "FeatureCollection",
"crs": { "type": "name", "properties": { "name": "urn:ogc:def:crs:OGC:1.3:CRS84" } },
"features": [
{ "type": "Feature", "properties": { "id": 42333, "count_point_id": 78415, "year": 2001, "region_id": 4, "local_authority_id": 10, "road_name": "A4087", "road_category": "PA", "road_type": "Major", "start_junction_road_name": "Toronnen, Glan Adda", "end_junction_road_name": "A5", "easting": 257250, "northing": 371250, "link_length_km": 2.0, "link_length_miles": 1.24, "sequence": 20.0, "ramp": null, "estimation_method": "Estimated", "estimation_method_detailed": "Estimated from nearby links", "direction_of_travel": "C", "pedal_cycles": 60, "two_wheeled_motor_vehicles": 128, "cars_and_taxis": 16532, "buses_and_coaches": 135, "lgvs": 1267, "hgvs_2_rigid_axle": 385, "hgvs_3_rigid_axle": 37, "hgvs_4_or_more_rigid_axle": 16, "hgvs_3_or_4_articulated_axle": 22, "hgvs_5_articulated_axle": 17, "hgvs_6_articulated_axle": 19, "all_hgvs": 496, "all_motor_vehicles": 18558 }, "geometry": { "type": "Point", "coordinates": [ -4.13946491, 53.21907153 ] } },
{ "type": "Feature", "properties": { "id": 202574, "count_point_id": 78415, "year": 2015, "region_id": 4, "local_authority_id": 10, "road_name": "A4087", "road_category": "PA", "road_type": "Major", "start_junction_road_name": "Toronnen, Glan Adda", "end_junction_road_name": "A5", "easting": 257250, "northing": 371250, "link_length_km": 2.0, "link_length_miles": 1.24, "sequence": 20.0, "ramp": 0.0, "estimation_method": "Estimated", "estimation_method_detailed": "Estimated from nearby links", "direction_of_travel": "C", "pedal_cycles": 14, "two_wheeled_motor_vehicles": 83, "cars_and_taxis": 17341, "buses_and_coaches": 150, "lgvs": 2661, "hgvs_2_rigid_axle": 243, "hgvs_3_rigid_axle": 35, "hgvs_4_or_more_rigid_axle": 30, "hgvs_3_or_4_articulated_axle": 9, "hgvs_5_articulated_axle": 29, "hgvs_6_articulated_axle": 21, "all_hgvs": 368, "all_motor_vehicles": 20603 }, "geometry": { "type": "Point", "coordinates": [ -4.13946491, 53.21907153 ] } },
{ "type": "Feature", "properties": { "id": 93814, "count_point_id": 78415, "year": 2012, "region_id": 4, "local_authority_id": 10, "road_name": "A4087", "road_category": "PA", "road_type": "Major", "start_junction_road_name": "Toronnen, Glan Adda", "end_junction_road_name": "A5", "easting": 257250, "northing": 371250, "link_length_km": 2.0, "link_length_miles": 1.24, "sequence": 20.0, "ramp": null, "estimation_method": "Estimated", "estimation_method_detailed": "Estimated from nearby links", "direction_of_travel": "C", "pedal_cycles": 18, "two_wheeled_motor_vehicles": 73, "cars_and_taxis": 17546, "buses_and_coaches": 145, "lgvs": 2268, "hgvs_2_rigid_axle": 246, "hgvs_3_rigid_axle": 28, "hgvs_4_or_more_rigid_axle": 25, "hgvs_3_or_4_articulated_axle": 10, "hgvs_5_articulated_axle": 32, "hgvs_6_articulated_axle": 19, "all_hgvs": 361, "all_motor_vehicles": 20394 }, "geometry": { "type": "Point", "coordinates": [ -4.13946491, 53.21907153 ] } },
{ "type": "Feature", "properties": { "id": 247814, "count_point_id": 78415, "year": 2017, "region_id": 4, "local_authority_id": 10, "road_name": "A4087", "road_category": "PA", "road_type": "Major", "start_junction_road_name": "Toronnen, Glan Adda", "end_junction_road_name": "A5", "easting": 257250, "northing": 371250, "link_length_km": 2.0, "link_length_miles": 1.24, "sequence": 20.0, "ramp": 0.0, "estimation_method": "Estimated", "estimation_method_detailed": "Estimated from nearby links", "direction_of_travel": "C", "pedal_cycles": 54, "two_wheeled_motor_vehicles": 81, "cars_and_taxis": 21196, "buses_and_coaches": 108, "lgvs": 1734, "hgvs_2_rigid_axle": 117, "hgvs_3_rigid_axle": 22, "hgvs_4_or_more_rigid_axle": 3, "hgvs_3_or_4_articulated_axle": 5, "hgvs_5_articulated_axle": 18, "hgvs_6_articulated_axle": 10, "all_hgvs": 176, "all_motor_vehicles": 23295 }, "geometry": { "type": "Point", "coordinates": [ -4.13946491, 53.21907153 ] } },
{ "type": "Feature", "properties": { "id": 174183, "count_point_id": 78415, "year": 2014, "region_id": 4, "local_authority_id": 10, "road_name": "A4087", "road_category": "PA", "road_type": "Major", "start_junction_road_name": "Toronnen, Glan Adda", "end_junction_road_name": "A5", "easting": 257250, "northing": 371250, "link_length_km": 2.0, "link_length_miles": 1.24, "sequence": 20.0, "ramp": 0.0, "estimation_method": "Estimated", "estimation_method_detailed": "Estimated from nearby links", "direction_of_travel": "C", "pedal_cycles": 14, "two_wheeled_motor_vehicles": 83, "cars_and_taxis": 17463, "buses_and_coaches": 148, "lgvs": 2444, "hgvs_2_rigid_axle": 233, "hgvs_3_rigid_axle": 31, "hgvs_4_or_more_rigid_axle": 29, "hgvs_3_or_4_articulated_axle": 7, "hgvs_5_articulated_axle": 28, "hgvs_6_articulated_axle": 21, "all_hgvs": 349, "all_motor_vehicles": 20487 }, "geometry": { "type": "Point", "coordinates": [ -4.13946491, 53.21907153 ] } }
]
}
