{
"type": "FeatureCollection",
"crs": { "type": "name", "properties": { "name": "urn:ogc:def:crs:OGC:1.3:CRS84" } },
"features": [
{ "type": "Feature", "properties": { "id": 231399, "count_point_id": 20644, "year": 2017, "region_id": 4, "local_authority_id": 17, "road_name": "A4109", "road_category": "PA", "road_type": "Major", "start_junction_road_name": "B4242", "end_junction_road_name": "A4221", "easting": 278440, "northing": 202779, "link_length_km": 15.6, "link_length_miles": 9.69, "sequence": 20.0, "ramp": 0.0, "estimation_method": "Counted", "estimation_method_detailed": "Manual count", "direction_of_travel": "N", "pedal_cycles": 8, "two_wheeled_motor_vehicles": 12, "cars_and_taxis": 2454, "buses_and_coaches": 31, "lgvs": 474, "hgvs_2_rigid_axle": 18, "hgvs_3_rigid_axle": 1, "hgvs_4_or_more_rigid_axle": 0, "hgvs_3_or_4_articulated_axle": 1, "hgvs_5_articulated_axle": 1, "hgvs_6_articulated_axle": 2, "all_hgvs": 23, "all_motor_vehicles": 2993 }, "geometry": { "type": "Point", "coordinates": [ -3.76079401, 51.71053599 ] } },
{ "type": "Feature", "properties": { "id": 231400, "count_point_id": 20644, "year": 2017, "region_id": 4, "local_authority_id": 17, "road_name": "A4109", "road_category": "PA", "road_type": "Major", "start_junction_road_name": "B4242", "end_junction_road_name": "A4221", "easting": 278440, "northing": 202779, "link_length_km": 15.6, "link_length_miles": 9.69, "sequence": 20.0, "ramp": 0.0, "estimation_method": "Counted", "estimation_method_detailed": "Manual count", "direction_of_travel": "S", "pedal_cycles": 6, "two_wheeled_motor_vehicles": 10, "cars_and_taxis": 2334, "buses_and_coaches": 35, "lgvs": 398, "hgvs_2_rigid_axle": 14, "hgvs_3_rigid_axle": 1, "hgvs_4_or_more_rigid_axle": 0, "hgvs_3_or_4_articulated_axle": 1, "hgvs_5_articulated_axle": 3, "hgvs_6_articulated_axle": 2, "all_hgvs": 21, "all_motor_vehicles": 2798 }, "geometry": { "type": "Point", "coordinates": [ -3.76079401, 51.71053599 ] } }
]
}
