{
"type": "FeatureCollection",
"crs": { "type": "name", "properties": { "name": "urn:ogc:def:crs:OGC:1.3:CRS84" } },
"features": [
{ "type": "Feature", "properties": { "id": 36961, "count_point_id": 990544, "year": 2002, "region_id": 4, "local_authority_id": 22, "road_name": "B4278", "road_category": "MB", "road_type": "Minor", "start_junction_road_name": null, "end_junction_road_name": null, "easting": 300120, "northing": 188020, "link_length_km": null, "link_length_miles": null, "sequence": null, "ramp": null, "estimation_method": "Estimated", "estimation_method_detailed": "Estimated using previous year's AADF on this link", "direction_of_travel": "E", "pedal_cycles": 2, "two_wheeled_motor_vehicles": 38, "cars_and_taxis": 2733, "buses_and_coaches": 54, "lgvs": 378, "hgvs_2_rigid_axle": 53, "hgvs_3_rigid_axle": 9, "hgvs_4_or_more_rigid_axle": 2, "hgvs_3_or_4_articulated_axle": 2, "hgvs_5_articulated_axle": 0, "hgvs_6_articulated_axle": 2, "all_hgvs": 68, "all_motor_vehicles": 3271 }, "geometry": { "type": "Point", "coordinates": [ -3.44290967, 51.58215994 ] } },
{ "type": "Feature", "properties": { "id": 36962, "count_point_id": 990544, "year": 2002, "region_id": 4, "local_authority_id": 22, "road_name": "B4278", "road_category": "MB", "road_type": "Minor", "start_junction_road_name": null, "end_junction_road_name": null, "easting": 300120, "northing": 188020, "link_length_km": null, "link_length_miles": null, "sequence": null, "ramp": null, "estimation_method": "Estimated", "estimation_method_detailed": "Estimated using previous year's AADF on this link", "direction_of_travel": "W", "pedal_cycles": 8, "two_wheeled_motor_vehicles": 22, "cars_and_taxis": 2777, "buses_and_coaches": 45, "lgvs": 352, "hgvs_2_rigid_axle": 58, "hgvs_3_rigid_axle": 2, "hgvs_4_or_more_rigid_axle": 1, "hgvs_3_or_4_articulated_axle": 0, "hgvs_5_articulated_axle": 0, "hgvs_6_articulated_axle": 0, "all_hgvs": 61, "all_motor_vehicles": 3257 }, "geometry": { "type": "Point", "coordinates": [ -3.44290967, 51.58215994 ] } }
]
}
